[
  {
    "EGGAHABAKMH": 1,
    "MPKOBAJFKAD": 3007,
    "maxCount": 4
  },
  {
    "EGGAHABAKMH": 2,
    "MPKOBAJFKAD": 3007,
    "maxCount": 4
  },
  {
    "EGGAHABAKMH": 2,
    "MPKOBAJFKAD": 2004,
    "maxCount": 2
  },
  {
    "EGGAHABAKMH": 3,
    "MPKOBAJFKAD": 5001,
    "maxCount": 3
  },
  {
    "EGGAHABAKMH": 3,
    "MPKOBAJFKAD": 5002,
    "maxCount": 1
  },
  {
    "EGGAHABAKMH": 3,
    "MPKOBAJFKAD": 5003,
    "maxCount": 1
  },
  {
    "EGGAHABAKMH": 3,
    "MPKOBAJFKAD": 2002,
    "maxCount": 5
  },
  {
    "EGGAHABAKMH": 4,
    "MPKOBAJFKAD": 3007,
    "maxCount": 2
  },
  {
    "EGGAHABAKMH": 4,
    "MPKOBAJFKAD": 5002,
    "maxCount": 2
  },
  {
    "EGGAHABAKMH": 4,
    "MPKOBAJFKAD": 2001,
    "maxCount": 2
  },
  {
    "EGGAHABAKMH": 5,
    "MPKOBAJFKAD": 3007,
    "maxCount": 2
  },
  {
    "EGGAHABAKMH": 5,
    "MPKOBAJFKAD": 5002,
    "maxCount": 2
  },
  {
    "EGGAHABAKMH": 5,
    "MPKOBAJFKAD": 2001,
    "maxCount": 5
  },
  {
    "EGGAHABAKMH": 5,
    "MPKOBAJFKAD": 3008,
    "maxCount": 1
  },
  {
    "EGGAHABAKMH": 6,
    "MPKOBAJFKAD": 3002,
    "maxCount": 3
  },
  {
    "EGGAHABAKMH": 6,
    "MPKOBAJFKAD": 5003,
    "maxCount": 2
  },
  {
    "EGGAHABAKMH": 7,
    "MPKOBAJFKAD": 3001,
    "maxCount": 1
  },
  {
    "EGGAHABAKMH": 7,
    "MPKOBAJFKAD": 3003,
    "maxCount": 1
  },
  {
    "EGGAHABAKMH": 7,
    "MPKOBAJFKAD": 5001,
    "maxCount": 1
  },
  {
    "EGGAHABAKMH": 8,
    "MPKOBAJFKAD": 3002,
    "maxCount": 1
  },
  {
    "EGGAHABAKMH": 8,
    "MPKOBAJFKAD": 5002,
    "maxCount": 3
  },
  {
    "EGGAHABAKMH": 8,
    "MPKOBAJFKAD": 3005,
    "maxCount": 1
  },
  {
    "EGGAHABAKMH": 9,
    "MPKOBAJFKAD": 5003,
    "maxCount": 1
  },
  {
    "EGGAHABAKMH": 9,
    "MPKOBAJFKAD": 3002,
    "maxCount": 2
  },
  {
    "EGGAHABAKMH": 10,
    "MPKOBAJFKAD": 3002,
    "maxCount": 1
  },
  {
    "EGGAHABAKMH": 10,
    "MPKOBAJFKAD": 3006,
    "maxCount": 3
  },
  {
    "EGGAHABAKMH": 11,
    "MPKOBAJFKAD": 3007,
    "maxCount": 3
  },
  {
    "EGGAHABAKMH": 11,
    "MPKOBAJFKAD": 4008,
    "maxCount": 1
  },
  {
    "EGGAHABAKMH": 11,
    "MPKOBAJFKAD": 4004,
    "maxCount": 5
  },
  {
    "EGGAHABAKMH": 12,
    "MPKOBAJFKAD": 5003,
    "maxCount": 2
  },
  {
    "EGGAHABAKMH": 12,
    "MPKOBAJFKAD": 3002,
    "maxCount": 1
  },
  {
    "EGGAHABAKMH": 12,
    "MPKOBAJFKAD": 3003,
    "maxCount": 3
  },
  {
    "EGGAHABAKMH": 12,
    "MPKOBAJFKAD": 3004,
    "maxCount": 3
  },
  {
    "EGGAHABAKMH": 12,
    "MPKOBAJFKAD": 2002,
    "maxCount": 2
  },
  {
    "EGGAHABAKMH": 13,
    "MPKOBAJFKAD": 3001,
    "maxCount": 1
  },
  {
    "EGGAHABAKMH": 13,
    "MPKOBAJFKAD": 3002,
    "maxCount": 3
  },
  {
    "EGGAHABAKMH": 13,
    "MPKOBAJFKAD": 3006,
    "maxCount": 1
  },
  {
    "EGGAHABAKMH": 13,
    "MPKOBAJFKAD": 3004,
    "maxCount": 2
  }
]