[
  {
    "interNPCId": 30069,
    "npcPosition": [
      0,
      0,
      -1
    ],
    "npcRotation": 180,
    "npcId": 30076,
    "markId": 415,
    "freeStyleId": 4090,
    "banConfig": "MusicGameEvent2"
  },
  {
    "interNPCId": 30070,
    "npcPosition": [
      0,
      0,
      -1
    ],
    "npcRotation": 180,
    "npcId": 30077,
    "markId": 414,
    "freeStyleId": 4090,
    "banConfig": "MusicGameEvent2"
  },
  {
    "interNPCId": 30071,
    "npcPosition": [
      0,
      0,
      -1
    ],
    "npcRotation": 180,
    "npcId": 30078,
    "markId": 413,
    "freeStyleId": 4090,
    "banConfig": "MusicGameEvent2"
  },
  {
    "interNPCId": 30072,
    "npcPosition": [
      0,
      0,
      -1
    ],
    "npcRotation": 180,
    "npcId": 30079,
    "markId": 412,
    "freeStyleId": 4090,
    "banConfig": "MusicGameEvent2"
  },
  {
    "interNPCId": 30073,
    "npcPosition": [
      0,
      0,
      -1
    ],
    "npcRotation": 180,
    "npcId": 30081,
    "markId": 411,
    "freeStyleId": 4090,
    "banConfig": "MusicGameEvent2"
  },
  {
    "interNPCId": 30074,
    "npcPosition": [
      0,
      0,
      -1
    ],
    "npcRotation": 180,
    "npcId": 30082,
    "markId": 410,
    "freeStyleId": 4090,
    "banConfig": "MusicGameEvent2"
  },
  {
    "interNPCId": 30075,
    "npcPosition": [
      0,
      0,
      -1
    ],
    "npcRotation": 180,
    "npcId": 30080,
    "markId": 409,
    "freeStyleId": 4090,
    "banConfig": "MusicGameEvent2"
  },
  {
    "interNPCId": 30076,
    "npcPosition": [],
    "banConfig": "MusicGameEvent3"
  }
]