{
    "Yelan_SkillUpgrade_1": [
        {
            "$type": "ModifyAbility",
            "abilityName": "Avatar_Yelan_ShootArrow_Bullet",
            "paramSpecial": "NormalAttack_01_DamagePercentage",
            "NEJDLLPMCPM": "%1",
            "JIPGCCEJFPC": 0.0
        },
        {
            "$type": "ModifyAbility",
            "abilityName": "Avatar_Yelan_ShootArrow_Bullet",
            "paramSpecial": "NormalAttack_02_DamagePercentage",
            "NEJDLLPMCPM": "%2",
            "JIPGCCEJFPC": 0.0
        },
        {
            "$type": "ModifyAbility",
            "abilityName": "Avatar_Yelan_ShootArrow_Bullet",
            "paramSpecial": "NormalAttack_03_DamagePercentage",
            "NEJDLLPMCPM": "%3",
            "JIPGCCEJFPC": 0.0
        },
        {
            "$type": "ModifyAbility",
            "abilityName": "Avatar_Yelan_ShootArrow_Bullet_Last",
            "paramSpecial": "NormalAttack_04_DamagePercentage",
            "NEJDLLPMCPM": "%4",
            "JIPGCCEJFPC": 0.0
        },
        {
            "$type": "ModifyAbility",
            "abilityName": "Avatar_Yelan_ShootArrow_Enchanted_WithOutWater",
            "paramSpecial": "DamageWithoutWater",
            "NEJDLLPMCPM": "%5",
            "JIPGCCEJFPC": 0.0
        },
        {
            "$type": "ModifyAbility",
            "abilityName": "Avatar_Yelan_ShootArrow_Enchanted_WithWater",
            "paramSpecial": "DamageWithWater",
            "NEJDLLPMCPM": "%6",
            "JIPGCCEJFPC": 0.0
        },
        {
            "$type": "ModifyAbility",
            "abilityName": "Avatar_Yelan_SneakArrow",
            "paramSpecial": "DamageWithWater_Sneak",
            "NEJDLLPMCPM": "%7",
            "JIPGCCEJFPC": 0.0
        },
        {
            "$type": "ModifyAbility",
            "abilityName": "Avatar_Yelan_SneakArrow_Extra_Before",
            "paramSpecial": "DamageWithWater_Sneak",
            "NEJDLLPMCPM": "%7",
            "JIPGCCEJFPC": 0.0
        },
        {
            "$type": "ModifyAbility",
            "abilityName": "Avatar_Yelan_SneakArrow_Extra_After",
            "paramSpecial": "DamageWithWater_Sneak",
            "NEJDLLPMCPM": "%7",
            "JIPGCCEJFPC": 0.0
        },
        {
            "$type": "ModifyAbility",
            "abilityName": "Avatar_Yelan_FallingAnthem",
            "paramSpecial": "FallingAnthem_Normal_Loop_Damage",
            "NEJDLLPMCPM": "%8",
            "JIPGCCEJFPC": 0.0
        },
        {
            "$type": "ModifyAbility",
            "abilityName": "Avatar_Yelan_FallingAnthem",
            "paramSpecial": "FallingAnthem_Normal_Rank_1_Damage",
            "NEJDLLPMCPM": "%9",
            "JIPGCCEJFPC": 0.0
        },
        {
            "$type": "ModifyAbility",
            "abilityName": "Avatar_Yelan_FallingAnthem",
            "paramSpecial": "FallingAnthem_Normal_Rank_2_Damage",
            "NEJDLLPMCPM": "%10",
            "JIPGCCEJFPC": 0.0
        }
    ],
    "Yelan_SkillUpgrade_2": [
        {
            "$type": "ModifyAbility",
            "abilityName": "Avatar_Yelan_ElementalArt_TriggerCollision",
            "paramSpecial": "ElementalArt_Damage_Ratio",
            "NEJDLLPMCPM": "%1",
            "JIPGCCEJFPC": 0.0
        },
        {
            "$type": "ModifyAbility",
            "abilityName": "Avatar_Yelan_ElementalArt_TriggerCollision",
            "paramSpecial": "ElementalArt_ResetSneak_Chance",
            "NEJDLLPMCPM": "%2",
            "JIPGCCEJFPC": 0.0
        },
        {
            "$type": "ModifyAbility",
            "abilityName": "Avatar_Yelan_ElementalArt_Check",
            "paramSpecial": "QuietStep_Max_Timer",
            "NEJDLLPMCPM": "%3",
            "JIPGCCEJFPC": 0.0
        }
    ],
    "Yelan_SkillUpgrade_3": [
        {
            "$type": "ModifyAbility",
            "abilityName": "Avatar_Yelan_ElementalBurst_Dice",
            "paramSpecial": "ElementalBurst_Strike_Damage",
            "NEJDLLPMCPM": "%1",
            "JIPGCCEJFPC": 0.0
        },
        {
            "$type": "ModifyAbility",
            "abilityName": "Avatar_Yelan_ElementalBurst_Dice_Bullet_01",
            "paramSpecial": "ElementalBurst_Bullet_Damage",
            "NEJDLLPMCPM": "%2",
            "JIPGCCEJFPC": 0.0
        },
        {
            "$type": "ModifyAbility",
            "abilityName": "Avatar_Yelan_ElementalBurst_Dice",
            "paramSpecial": "Dice_Timer",
            "NEJDLLPMCPM": "%3",
            "JIPGCCEJFPC": 0.0
        }
    ],
    "Yelan_PermanentSkill_1": [
        {
            "$type": "AddAbility",
            "abilityName": "Avatar_Yelan_PermanentSkill_1"
        },
        {
            "$type": "ModifyAbility",
            "abilityName": "Avatar_Yelan_PermanentSkill_1",
            "paramSpecial": "Hp_Ratio_Lv1",
            "NEJDLLPMCPM": "%1",
            "JIPGCCEJFPC": 0.0
        },
        {
            "$type": "ModifyAbility",
            "abilityName": "Avatar_Yelan_PermanentSkill_1",
            "paramSpecial": "Hp_Ratio_Lv2",
            "NEJDLLPMCPM": "%2",
            "JIPGCCEJFPC": 0.0
        },
        {
            "$type": "ModifyAbility",
            "abilityName": "Avatar_Yelan_PermanentSkill_1",
            "paramSpecial": "Hp_Ratio_Lv3",
            "NEJDLLPMCPM": "%3",
            "JIPGCCEJFPC": 0.0
        },
        {
            "$type": "ModifyAbility",
            "abilityName": "Avatar_Yelan_PermanentSkill_1",
            "paramSpecial": "Hp_Ratio_Lv4",
            "NEJDLLPMCPM": "%4",
            "JIPGCCEJFPC": 0.0
        }
    ],
    "Yelan_PermanentSkill_2": [
        {
            "$type": "UnlockTalentParam",
            "abilityName": "Avatar_Yelan_ElementalBurst_Dice",
            "talentParam": "Yelan_PermanentSkill_2"
        },
        {
            "$type": "ModifyAbility",
            "abilityName": "Avatar_Yelan_ElementalBurst_Dice",
            "paramSpecial": "Base_Damage_Ratio",
            "NEJDLLPMCPM": "%1",
            "JIPGCCEJFPC": 0.0
        },
        {
            "$type": "ModifyAbility",
            "abilityName": "Avatar_Yelan_ElementalBurst_Dice",
            "paramSpecial": "Per_Damage_Ratio",
            "NEJDLLPMCPM": "%2",
            "JIPGCCEJFPC": 0.0
        },
        {
            "$type": "ModifyAbility",
            "abilityName": "Avatar_Yelan_ElementalBurst_Dice",
            "paramSpecial": "Tick_Time",
            "NEJDLLPMCPM": "%3",
            "JIPGCCEJFPC": 0.0
        },
        {
            "$type": "ModifyAbility",
            "abilityName": "Avatar_Yelan_ElementalBurst_Dice",
            "paramSpecial": "Max_Level",
            "NEJDLLPMCPM": "%4",
            "JIPGCCEJFPC": 0.0
        }
    ],
    "Yelan_Constellation_1": [
        {
            "$type": "ModifySkillPoint",
            "overtime": 10607,
            "IGEBKIHPOIF": 1
        }
    ],
    "Yelan_Constellation_2": [
        {
            "$type": "UnlockTalentParam",
            "abilityName": "Avatar_Yelan_ElementalBurst_Dice_TriggerBullet",
            "talentParam": "Yelan_Constellation_2"
        },
        {
            "$type": "UnlockTalentParam",
            "abilityName": "Avatar_Yelan_ElementalBurst_Dice_TriggerBullet_Extra",
            "talentParam": "Yelan_Constellation_2"
        },
        {
            "$type": "ModifyAbility",
            "abilityName": "Avatar_Yelan_ElementalBurst_Dice_Bullet_Extra",
            "paramSpecial": "Constellation_2_Damage",
            "NEJDLLPMCPM": "%1",
            "JIPGCCEJFPC": 0.0
        },
        {
            "$type": "ModifyAbility",
            "abilityName": "Avatar_Yelan_ElementalBurst_Dice_TriggerBullet",
            "paramSpecial": "Constellation_2_CD",
            "NEJDLLPMCPM": "%2",
            "JIPGCCEJFPC": 0.0
        },
        {
            "$type": "ModifyAbility",
            "abilityName": "Avatar_Yelan_ElementalBurst_Dice_TriggerBullet_Extra",
            "paramSpecial": "Constellation_2_CD",
            "NEJDLLPMCPM": "%2",
            "JIPGCCEJFPC": 0.0
        }
    ],
    "Yelan_Constellation_3": [
        {
            "$type": "AddTalentExtraLevel",
            "GICDOCFMKHF": "AvatarSkill",
            "OJOFFKLNAHN": 9,
            "OOCOLBNBEHL": 3
        }
    ],
    "Yelan_Constellation_4": [
        {
            "$type": "AddAbility",
            "abilityName": "Avatar_Yelan_Constellation_4"
        },
        {
            "$type": "UnlockTalentParam",
            "abilityName": "Avatar_Yelan_ElementalArt_TriggerCollision",
            "talentParam": "Yelan_Constellation_4"
        },
        {
            "$type": "ModifyAbility",
            "abilityName": "Avatar_Yelan_Constellation_4",
            "paramSpecial": "Hp_Ratio",
            "NEJDLLPMCPM": "%1",
            "JIPGCCEJFPC": 0.0
        },
        {
            "$type": "ModifyAbility",
            "abilityName": "Avatar_Yelan_Constellation_4",
            "paramSpecial": "Duration",
            "NEJDLLPMCPM": "%2",
            "JIPGCCEJFPC": 0.0
        },
        {
            "$type": "ModifyAbility",
            "abilityName": "Avatar_Yelan_Constellation_4",
            "paramSpecial": "Max_Level",
            "NEJDLLPMCPM": "%3",
            "JIPGCCEJFPC": 0.0
        }
    ],
    "Yelan_Constellation_5": [
        {
            "$type": "AddTalentExtraLevel",
            "GICDOCFMKHF": "AvatarSkill",
            "OJOFFKLNAHN": 2,
            "OOCOLBNBEHL": 3
        }
    ],
    "Yelan_Constellation_6": [
        {
            "$type": "AddAbility",
            "abilityName": "Avatar_Yelan_Constellation_6"
        },
        {
            "$type": "UnlockTalentParam",
            "abilityName": "Avatar_Yelan_ElementalBurst",
            "talentParam": "Yelan_Constellation_6"
        },
        {
            "$type": "ModifyAbility",
            "abilityName": "Avatar_Yelan_Constellation_6",
            "paramSpecial": "Atk_Count",
            "NEJDLLPMCPM": "%1",
            "JIPGCCEJFPC": 0.0
        },
        {
            "$type": "ModifyAbility",
            "abilityName": "Avatar_Yelan_Constellation_6",
            "paramSpecial": "Duration",
            "NEJDLLPMCPM": "%2",
            "JIPGCCEJFPC": 0.0
        },
        {
            "$type": "ModifyAbility",
            "abilityName": "Avatar_Yelan_SneakArrow_Extra_Before",
            "paramSpecial": "Constellation_6_Ratio",
            "NEJDLLPMCPM": "%3",
            "JIPGCCEJFPC": 0.0
        },
        {
            "$type": "ModifyAbility",
            "abilityName": "Avatar_Yelan_SneakArrow_Extra_After",
            "paramSpecial": "Constellation_6_Ratio",
            "NEJDLLPMCPM": "%3",
            "JIPGCCEJFPC": 0.0
        }
    ]
}