[
    {
        "Default": {
            "$type": "ConfigAbility",
            "abilityName": "Monster_Abyss_Water_SpecialsState",
            "abilityMixins": [
                {
                    "$type": "DoActionByStateIDMixin",
                    "stateIDs": [
                        "Sacrifice",
                        "TurnToSacrifice"
                    ],
                    "OFLAPMGKHHE": [
                        {
                            "$type": "ByTargetGlobalValue",
                            "HJJEAOMEOFI": "_ABILITY_ABYSS_WATER_ELEMENTSHIELD",
                            "value": 1.0,
                            "EODMLMGMLNP": true
                        }
                    ],
                    "JLLNCKPFKLD": [
                        {
                            "$type": "ByTargetGlobalValue",
                            "HJJEAOMEOFI": "_ABILITY_ABYSS_WATER_ELEMENTSHIELD",
                            "value": 0.0,
                            "EODMLMGMLNP": true
                        }
                    ],
                    "KELPBOLPMNI": [
                        {
                            "$type": "TriggerAbility",
                            "abilityName": "Abyss_Water_ElementShield_Remove_NoBroken"
                        }
                    ],
                    "MCFCEOACJEB": [
                        {
                            "$type": "SetPoseInt",
                            "intID": "ElementState",
                            "weight": 2
                        },
                        {
                            "$type": "TriggerAbility",
                            "abilityName": "Abyss_Water_ElementShield"
                        },
                        {
                            "$type": "TriggerAbility",
                            "abilityName": "Abyss_Water_ElementShield_Effect"
                        }
                    ]
                }
            ]
        }
    },
    {
        "Default": {
            "$type": "ConfigAbility",
            "abilityName": "Abyss_Water_ElementShield_Remove_NoBroken",
            "HKBHLMNEMKM": [
                {
                    "$type": "RemoveUniqueModifier",
                    "modifierName": "UNIQUE_Abyss_Water_ElementShield"
                },
                {
                    "$type": "SetPoseInt",
                    "intID": "ElementState",
                    "weight": 2
                },
                {
                    "$type": "ResetAnimatorTrigger",
                    "triggerID": "ShiledBrokenTrigger"
                }
            ]
        }
    },
    {
        "Default": {
            "$type": "ConfigAbility",
            "abilityName": "Abyss_Water_SacrificeAlert",
            "HKBHLMNEMKM": [
                {
                    "$type": "SetPoseInt",
                    "intID": "ElementState",
                    "weight": 2
                },
                {
                    "$type": "TriggerAbility",
                    "abilityName": "Abyss_Water_ElementShield"
                },
                {
                    "$type": "TriggerAbility",
                    "abilityName": "Abyss_Water_ElementShield_Effect"
                }
            ]
        }
    },
    {
        "Default": {
            "$type": "ConfigAbility",
            "abilityName": "Abyss_Water_WeaponElement",
            "abilityMixins": [
                {
                    "$type": "AttachToPoseIDMixin",
                    "poseIDs": [
                        201,
                        300,
                        301
                    ],
                    "modifierName": "WeaponEffect"
                }
            ],
            "HNEIEGHMLKH": {
                "WeaponEffect": {
                    "modifierName": "",
                    "elementDurability": 100.0,
                    "onAdded": [
                        {
                            "$type": "AttachEffect",
                            "effectPattern": "Eff_Monster_Abyss_Water_WeaponElement"
                        }
                    ],
                    "OGFFGLGEOGF": [
                        {
                            "$type": "RemoveModifier",
                            "modifierName": "WeaponEffect"
                        }
                    ]
                }
            }
        }
    },
    {
        "Default": {
            "$type": "ConfigAbility",
            "abilityName": "Abyss_Water_ElementShield",
            "abilityMixins": [
                {
                    "$type": "AttachToPoseIDMixin",
                    "poseIDs": [
                        300,
                        301,
                        302
                    ],
                    "modifierName": "Abyss_Water_ElementShield_RecoverHandler"
                }
            ],
            "EDDGGPMFDGK": {
                "ElementShield_DurabilityImprove": 0.0
            },
            "HNEIEGHMLKH": {
                "Abyss_Water_ElementShield_RecoverHandler": {
                    "modifierName": "",
                    "elementDurability": 100.0,
                    "AMJKBHJBBGN": [
                        {
                            "$type": "ApplyModifier",
                            "modifierName": "UNIQUE_Abyss_Water_ElementShield"
                        }
                    ]
                },
                "UNIQUE_MonsterEliteAffix_DefaultState": {
                    "modifierName": "",
                    "IEOFBCGJGEK": true,
                    "elementDurability": 100.0,
                    "onAdded": [
                        {
                            "$type": "UseSkillEliteSet",
                            "AFIOIAPCKEJ": 1
                        }
                    ]
                },
                "UNIQUE_Abyss_Water_ElementShield": {
                    "FGJPBKGPNJJ": "Unique",
                    "modifierName": "",
                    "IEOFBCGJGEK": true,
                    "elementType": "Water",
                    "elementDurability": [
                        300.0,
                        "ElementShield_DurabilityImprove",
                        "Mul",
                        300.0,
                        "Add"
                    ],
                    "modifierMixins": [
                        {
                            "$type": "ElementShieldMixin",
                            "elementType": "Water",
                            "FMAPKFDKKPB": "",
                            "KFDBBJLMOKJ": 360.0,
                            "PDGJDMOFOAO": 1.0,
                            "damageRatio": 0.20000000298023224,
                            "HMLKELJFCKD": [
                                {
                                    "$type": "Predicated",
                                    "NPHOOPNDCAC": "Target",
                                    "ELDBAFHCOBL": [
                                        {
                                            "$type": "ByEntityTypes",
                                            "entityTypes": [
                                                "Avatar"
                                            ]
                                        }
                                    ],
                                    "NCNDEAPMKCP": [
                                        {
                                            "$type": "SetGlobalDir",
                                            "NPHOOPNDCAC": "Target",
                                            "HJJEAOMEOFI": "_ABILITY_ABYSS_WATER_ELEMENTSHIELD_HIT",
                                            "NGDMCBABOJA": {
                                                "$type": "ConfigBornBySelf",
                                                "NHPNHKBMAEO": {
                                                    "$type": "ConfigDirectionByLookAtEntity"
                                                }
                                            },
                                            "OGADOPDNBMM": false
                                        }
                                    ],
                                    "BMIOBLGLPIM": [
                                        {
                                            "$type": "SetGlobalDir",
                                            "NPHOOPNDCAC": "TargetOriginOwner",
                                            "HJJEAOMEOFI": "_ABILITY_ABYSS_WATER_ELEMENTSHIELD_HIT",
                                            "NGDMCBABOJA": {
                                                "$type": "ConfigBornBySelf",
                                                "NHPNHKBMAEO": {
                                                    "$type": "ConfigDirectionByLookAtEntity"
                                                }
                                            },
                                            "OGADOPDNBMM": false
                                        }
                                    ]
                                },
                                {
                                    "$type": "FireEffect",
                                    "effectPattern": "Eff_Monster_Abyss_Water_ElementShield_Hit_Invalid",
                                    "NGDMCBABOJA": {
                                        "$type": "ConfigBornByTarget",
                                        "NHPNHKBMAEO": {
                                            "$type": "ConfigDirectionByGlobalValue",
                                            "MICIJLHMIIH": "_ABILITY_ABYSS_WATER_ELEMENTSHIELD_HIT"
                                        }
                                    }
                                },
                                {
                                    "$type": "SendEffectTrigger",
                                    "MOCGJNIDDAI": "BeHitInvalid",
                                    "effectPattern": "Eff_Monster_Abyss_Water_ElementShield_BS"
                                }
                            ],
                            "FFOEHJLIDFC": [
                                {
                                    "$type": "Predicated",
                                    "NPHOOPNDCAC": "Target",
                                    "ELDBAFHCOBL": [
                                        {
                                            "$type": "ByEntityTypes",
                                            "entityTypes": [
                                                "Avatar"
                                            ]
                                        }
                                    ],
                                    "NCNDEAPMKCP": [
                                        {
                                            "$type": "SetGlobalDir",
                                            "NPHOOPNDCAC": "Target",
                                            "HJJEAOMEOFI": "_ABILITY_ABYSS_WATER_ELEMENTSHIELD_HIT",
                                            "NGDMCBABOJA": {
                                                "$type": "ConfigBornBySelf",
                                                "NHPNHKBMAEO": {
                                                    "$type": "ConfigDirectionByLookAtEntity"
                                                }
                                            },
                                            "OGADOPDNBMM": false
                                        }
                                    ],
                                    "BMIOBLGLPIM": [
                                        {
                                            "$type": "SetGlobalDir",
                                            "NPHOOPNDCAC": "TargetOriginOwner",
                                            "HJJEAOMEOFI": "_ABILITY_ABYSS_WATER_ELEMENTSHIELD_HIT",
                                            "NGDMCBABOJA": {
                                                "$type": "ConfigBornBySelf",
                                                "NHPNHKBMAEO": {
                                                    "$type": "ConfigDirectionByLookAtEntity"
                                                }
                                            },
                                            "OGADOPDNBMM": false
                                        }
                                    ]
                                },
                                {
                                    "$type": "FireEffect",
                                    "effectPattern": "Eff_Monster_Abyss_Water_ElementShield_Hit",
                                    "NGDMCBABOJA": {
                                        "$type": "ConfigBornByTarget",
                                        "NHPNHKBMAEO": {
                                            "$type": "ConfigDirectionByGlobalValue",
                                            "MICIJLHMIIH": "_ABILITY_ABYSS_WATER_ELEMENTSHIELD_HIT"
                                        }
                                    }
                                },
                                {
                                    "$type": "SendEffectTrigger",
                                    "MOCGJNIDDAI": "BeHit",
                                    "effectPattern": "Eff_Monster_Abyss_Water_ElementShield_BS"
                                }
                            ],
                            "NGOKEFIDFCJ": true,
                            "HJAIAEACKHM": true
                        },
                        {
                            "$type": "VelocityForceMixin",
                            "MPGPCCEHFGL": [
                                "WindZoneType"
                            ]
                        }
                    ],
                    "properties": {
                        "Actor_EndureDelta": 0.0
                    },
                    "onAdded": [
                        {
                            "$type": "AddGlobalValue",
                            "value": 1.0,
                            "HJJEAOMEOFI": "_ABILITY_ABYSS_WATER_ELEMENTSHIELD",
                            "EODOIECEPEF": true,
                            "JDHHMBHOOEC": 1.0,
                            "KHAHOELDONA": 0.0
                        },
                        {
                            "$type": "ApplyModifier",
                            "modifierName": "UNIQUE_Abyss_Water_MoveOnWaterHandler"
                        },
                        {
                            "$type": "AttachAbilityStateResistance",
                            "KPGAIMMIKDA": 14001
                        }
                    ],
                    "onRemoved": [
                        {
                            "$type": "SetAnimatorTrigger",
                            "triggerID": "ShiledBrokenTrigger"
                        },
                        {
                            "$type": "SetPoseInt",
                            "intID": "ElementState"
                        },
                        {
                            "$type": "AddGlobalValue",
                            "value": -1.0,
                            "HJJEAOMEOFI": "_ABILITY_ABYSS_WATER_ELEMENTSHIELD",
                            "EODOIECEPEF": true,
                            "JDHHMBHOOEC": 1.0,
                            "KHAHOELDONA": 0.0
                        },
                        {
                            "$type": "RemoveUniqueModifier",
                            "predicates": [
                                {
                                    "$type": "ByTargetGlobalValue",
                                    "HJJEAOMEOFI": "_RETURNTOBORN_TAG_",
                                    "value": 0.0,
                                    "ONPJJFKDCED": "NoneOrEqual"
                                }
                            ],
                            "modifierName": "UNIQUE_Abyss_Water_MoveOnWaterHandler"
                        },
                        {
                            "$type": "RemoveUniqueModifier",
                            "modifierName": "UNIQUE_Abyss_Water_ElementShield_Effect"
                        }
                    ],
                    "onBeingHit": [
                        {
                            "$type": "DamageByAttackValue",
                            "NPHOOPNDCAC": "Target",
                            "predicates": [
                                {
                                    "$type": "ByTargetGlobalValue",
                                    "HJJEAOMEOFI": "_ELITEAFFIX_DEFENCE_ENHANCE",
                                    "value": 1.0,
                                    "EODMLMGMLNP": true
                                },
                                {
                                    "$type": "ByEntityTypes",
                                    "entityTypes": [
                                        "Avatar"
                                    ]
                                },
                                {
                                    "$type": "ByAnimatorFloat",
                                    "NPHOOPNDCAC": "Caster",
                                    "GMFCOCAJBDM": "GreaterOrEqual",
                                    "value": 301.0,
                                    "MOCGJNIDDAI": "PoseID"
                                }
                            ],
                            "attackInfo": {
                                "attackTag": "",
                                "attenuationTag": "",
                                "attenuationGroup": "default",
                                "attackProperty": {
                                    "bonusCriticalHurt": 0.0,
                                    "damagePercentageRatio": 0.0,
                                    "elementType": "Water",
                                    "elementDurability": 25.0,
                                    "enBreak": 0.0
                                },
                                "hitPattern": {
                                    "onHitEffectName": "none",
                                    "hitImpulseType": "LV0",
                                    "muteHitText": true
                                }
                            }
                        },
                        {
                            "$type": "DamageByAttackValue",
                            "NPHOOPNDCAC": "TargetOwner",
                            "predicates": [
                                {
                                    "$type": "ByTargetGlobalValue",
                                    "HJJEAOMEOFI": "_ELITEAFFIX_DEFENCE_ENHANCE",
                                    "value": 1.0,
                                    "EODMLMGMLNP": true
                                },
                                {
                                    "$type": "ByEntityTypes",
                                    "entityTypes": [
                                        "Avatar"
                                    ]
                                },
                                {
                                    "$type": "ByAnimatorFloat",
                                    "NPHOOPNDCAC": "Caster",
                                    "GMFCOCAJBDM": "GreaterOrEqual",
                                    "value": 301.0,
                                    "MOCGJNIDDAI": "PoseID"
                                }
                            ],
                            "attackInfo": {
                                "attackTag": "",
                                "attenuationTag": "",
                                "attenuationGroup": "default",
                                "attackProperty": {
                                    "bonusCriticalHurt": 0.0,
                                    "damagePercentageRatio": 0.0,
                                    "elementType": "Water",
                                    "elementDurability": 25.0,
                                    "enBreak": 0.0
                                },
                                "hitPattern": {
                                    "onHitEffectName": "none",
                                    "hitImpulseType": "LV0",
                                    "muteHitText": true
                                }
                            }
                        }
                    ],
                    "OGFFGLGEOGF": [
                        {
                            "$type": "RemoveUniqueModifier",
                            "modifierName": "UNIQUE_Abyss_Water_ElementShield"
                        }
                    ]
                },
                "UNIQUE_Abyss_Water_MoveOnWaterHandler": {
                    "modifierName": "",
                    "IEOFBCGJGEK": true,
                    "elementDurability": 100.0,
                    "modifierMixins": [
                        {
                            "$type": "EnableCharacterMoveOnWaterMixin"
                        }
                    ]
                }
            },
            "onAdded": [
                {
                    "$type": "SetGlobalValueToOverrideMap",
                    "globalValueKey": "_MONSTERAFFIX_ELEMENTSHIELD_DURABILITYIMPROVE",
                    "OGAHELLALBB": "ElementShield_DurabilityImprove"
                },
                {
                    "$type": "ApplyModifier",
                    "predicates": [
                        {
                            "$type": "ByTargetGlobalValue",
                            "HJJEAOMEOFI": "_ELITEAFFIX_TAG",
                            "value": 0.0,
                            "ONPJJFKDCED": "NoneOrEqual"
                        }
                    ],
                    "modifierName": "UNIQUE_MonsterEliteAffix_DefaultState"
                },
                {
                    "$type": "SetPoseInt",
                    "intID": "ElementState",
                    "weight": 2
                },
                {
                    "$type": "ApplyModifier",
                    "modifierName": "UNIQUE_Abyss_Water_ElementShield"
                }
            ],
            "HKBHLMNEMKM": [
                {
                    "$type": "SetPoseInt",
                    "intID": "ElementState",
                    "weight": 2
                },
                {
                    "$type": "ApplyModifier",
                    "modifierName": "UNIQUE_Abyss_Water_ElementShield"
                }
            ]
        }
    },
    {
        "Default": {
            "$type": "ConfigAbility",
            "abilityName": "Abyss_Water_ElementShield_Effect",
            "abilityMixins": [
                {
                    "$type": "AttachToPoseIDMixin",
                    "poseIDs": [
                        300,
                        301,
                        302
                    ],
                    "modifierName": "Abyss_Water_ElementShield_Effect_RecoverHandler"
                }
            ],
            "HNEIEGHMLKH": {
                "Abyss_Water_ElementShield_Effect_RecoverHandler": {
                    "modifierName": "",
                    "elementDurability": 100.0,
                    "AMJKBHJBBGN": [
                        {
                            "$type": "ApplyModifier",
                            "modifierName": "UNIQUE_Abyss_Water_ElementShield_Effect"
                        }
                    ]
                },
                "UNIQUE_Abyss_Water_ElementShield_Effect": {
                    "FGJPBKGPNJJ": "Unique",
                    "modifierName": "",
                    "IEOFBCGJGEK": true,
                    "elementDurability": 100.0,
                    "onAdded": [
                        {
                            "$type": "EnableHitBoxByName",
                            "EACGOCFODIC": [
                                "HitBox_ElementShield"
                            ],
                            "PAHBCOACBAI": true
                        },
                        {
                            "$type": "EnableHitBoxByName",
                            "EACGOCFODIC": [
                                "HitBox",
                                "HeadBox"
                            ]
                        },
                        {
                            "$type": "EnablePushColliderName",
                            "LEHFIPJFKBC": [
                                "PushCollider_ElementShield"
                            ],
                            "PAHBCOACBAI": true
                        },
                        {
                            "$type": "AttachEffect",
                            "effectPattern": "Eff_Monster_Abyss_Water_ElementShield_BS"
                        }
                    ],
                    "onRemoved": [
                        {
                            "$type": "EnableHitBoxByName",
                            "EACGOCFODIC": [
                                "HitBox_ElementShield"
                            ]
                        },
                        {
                            "$type": "EnableHitBoxByName",
                            "EACGOCFODIC": [
                                "HitBox",
                                "HeadBox"
                            ],
                            "PAHBCOACBAI": true
                        },
                        {
                            "$type": "EnablePushColliderName",
                            "LEHFIPJFKBC": [
                                "PushCollider_ElementShield"
                            ]
                        }
                    ]
                }
            },
            "HKBHLMNEMKM": [
                {
                    "$type": "ApplyModifier",
                    "predicates": [
                        {
                            "$type": "ByTargetGlobalValue",
                            "HJJEAOMEOFI": "_ABILITY_ABYSS_WATER_ELEMENTSHIELD",
                            "value": 1.0
                        }
                    ],
                    "modifierName": "UNIQUE_Abyss_Water_ElementShield_Effect"
                }
            ]
        }
    },
    {
        "Default": {
            "$type": "ConfigAbility",
            "abilityName": "Abyss_Water_ElementShield_Remove",
            "HKBHLMNEMKM": [
                {
                    "$type": "RemoveUniqueModifier",
                    "modifierName": "UNIQUE_Abyss_Water_ElementShield"
                }
            ]
        }
    },
    {
        "Default": {
            "$type": "ConfigAbility",
            "abilityName": "Abyss_Water_DizzyTimer",
            "abilityMixins": [
                {
                    "$type": "AttachToPoseIDMixin",
                    "poseIDs": [
                        100,
                        101
                    ],
                    "modifierName": "Abyss_Water_DizzyTimer_Handler"
                }
            ],
            "EDDGGPMFDGK": {
                "ElementShield_GapReduce": 0.0
            },
            "HNEIEGHMLKH": {
                "Abyss_Water_DizzyTimer_Handler": {
                    "modifierName": "",
                    "elementDurability": 100.0,
                    "onAdded": [
                        {
                            "$type": "ApplyModifier",
                            "modifierName": "UNIQUE_Abyss_Water_DizzyTimer"
                        }
                    ],
                    "AMJKBHJBBGN": [
                        {
                            "$type": "ApplyModifier",
                            "modifierName": "UNIQUE_Abyss_Water_DizzyTimer"
                        }
                    ]
                },
                "UNIQUE_Abyss_Water_DizzyTimer": {
                    "FGJPBKGPNJJ": "Unique",
                    "modifierName": "",
                    "IEOFBCGJGEK": true,
                    "GMIMMDOGGIO": [
                        12.0,
                        "ElementShield_GapReduce",
                        "Mul",
                        12.0,
                        "Add"
                    ],
                    "elementDurability": 100.0,
                    "properties": {
                        "Actor_EndureDelta": 3.0
                    },
                    "onRemoved": [
                        {
                            "$type": "SetPoseInt",
                            "predicates": [
                                {
                                    "$type": "ByTargetGlobalValue",
                                    "HJJEAOMEOFI": "_ABILITY_ABYSS_WATER_ELEMENTSHIELD",
                                    "value": 0.0,
                                    "ONPJJFKDCED": "NoneOrEqual"
                                }
                            ],
                            "intID": "ElementState",
                            "weight": 1
                        }
                    ]
                }
            },
            "onAdded": [
                {
                    "$type": "SetGlobalValueToOverrideMap",
                    "globalValueKey": "_MONSTERAFFIX_ELEMENTSHIELD_GAPREDUCE",
                    "OGAHELLALBB": "ElementShield_GapReduce"
                }
            ]
        }
    },
    {
        "Default": {
            "$type": "ConfigAbility",
            "abilityName": "Abyss_Water_GatherStart",
            "abilityMixins": [
                {
                    "$type": "AttachToStateIDMixin",
                    "stateIDs": [
                        "GatherStart",
                        "GatherLoop",
                        "GatherSuccess_Alert"
                    ],
                    "modifierName": "GatherState"
                },
                {
                    "$type": "AttachToPoseIDMixin",
                    "poseIDs": [
                        201
                    ],
                    "modifierName": "GatherEndure"
                }
            ],
            "HNEIEGHMLKH": {
                "GatherEndure": {
                    "modifierName": "",
                    "elementDurability": 100.0,
                    "properties": {
                        "Actor_EndureDelta": 0.4000000059604645
                    }
                },
                "GatherState": {
                    "modifierName": "",
                    "elementDurability": 100.0,
                    "onAdded": [
                        {
                            "$type": "AddGlobalValue",
                            "value": 1.0,
                            "HJJEAOMEOFI": "_ABILITY_ABYSS_WATER_GATHER",
                            "EODOIECEPEF": true,
                            "JDHHMBHOOEC": 1.0,
                            "KHAHOELDONA": 0.0
                        },
                        {
                            "$type": "AddGlobalValue",
                            "value": 1.0,
                            "HJJEAOMEOFI": "_GATHERFAILEDSTATE_",
                            "EODOIECEPEF": true,
                            "JDHHMBHOOEC": 1.0,
                            "KHAHOELDONA": 1.0
                        }
                    ],
                    "onRemoved": [
                        {
                            "$type": "SetPoseInt",
                            "predicates": [
                                {
                                    "$type": "ByTargetGlobalValue",
                                    "HJJEAOMEOFI": "_ABILITY_ABYSS_WATER_ELEMENTSHIELD",
                                    "value": 0.0,
                                    "ONPJJFKDCED": "NoneOrEqual"
                                }
                            ],
                            "intID": "ElementState"
                        },
                        {
                            "$type": "TriggerAbility",
                            "otherTargets": {
                                "$type": "SelectTargetsByChildren",
                                "APIAFGPIIHE": 42201004
                            },
                            "abilityName": "Abyss_Water_WaterBall_Explode"
                        },
                        {
                            "$type": "TriggerAbility",
                            "otherTargets": {
                                "$type": "SelectTargetsByChildren",
                                "APIAFGPIIHE": 42201005
                            },
                            "abilityName": "Abyss_Water_Bubble_Explode"
                        }
                    ]
                }
            }
        }
    },
    {
        "Default": {
            "$type": "ConfigAbility",
            "abilityName": "Abyss_Water_GatherLoop",
            "abilityMixins": [
                {
                    "$type": "AttachToStateIDMixin",
                    "stateIDs": [
                        "GatherLoop"
                    ],
                    "modifierName": "GatherLoop_Effect"
                },
                {
                    "$type": "AttachToStateIDMixin",
                    "stateIDs": [
                        "GatherLoop"
                    ],
                    "modifierName": "Gather_CreateBall"
                },
                {
                    "$type": "AttachToStateIDMixin",
                    "stateIDs": [
                        "GatherLoop"
                    ],
                    "modifierName": "Gather_CreateBubble"
                }
            ],
            "HNEIEGHMLKH": {
                "GatherLoop_Effect": {
                    "modifierName": "",
                    "elementDurability": 100.0,
                    "onAdded": [
                        {
                            "$type": "AttachEffect",
                            "effectPattern": "Eff_Monster_Abyss_Water_Gather"
                        },
                        {
                            "$type": "AttachEffect",
                            "effectPattern": "Eff_Monster_Abyss_Water_WeaponElement"
                        }
                    ]
                },
                "Gather_CreateBall": {
                    "modifierName": "",
                    "elementDurability": 100.0,
                    "IKKMDDLDLIN": 0.5,
                    "PBDDACFFPOE": [
                        {
                            "$type": "SetGlobalPos",
                            "HJJEAOMEOFI": "Gather_BallPos",
                            "NGDMCBABOJA": {
                                "$type": "ConfigBornByTarget",
                                "HAGMNJAHNLG": {
                                    "$type": "BornRandomFromCenter",
                                    "LJCNOPEIJEF": 1.0,
                                    "MFBOELKCPDP": 7.0
                                }
                            }
                        },
                        {
                            "$type": "TriggerBullet",
                            "NGAAOMEHOGE": 42201004,
                            "NGDMCBABOJA": {
                                "$type": "ConfigBornByGlobalValue",
                                "NHPNHKBMAEO": {
                                    "$type": "ConfigDirectionByWorld",
                                    "GLNBFGDJBAJ": {
                                        "_x": -90.0
                                    }
                                },
                                "GDENJEFPMGC": "Gather_BallPos",
                                "MICIJLHMIIH": ""
                            }
                        }
                    ]
                },
                "Gather_CreateBubble": {
                    "modifierName": "",
                    "elementDurability": 100.0,
                    "IKKMDDLDLIN": 1.0,
                    "PBDDACFFPOE": [
                        {
                            "$type": "SetGlobalPos",
                            "HJJEAOMEOFI": "Gather_BubblePos",
                            "NGDMCBABOJA": {
                                "$type": "ConfigBornByTarget",
                                "HAGMNJAHNLG": {
                                    "$type": "BornRandomFromCenter",
                                    "LJCNOPEIJEF": 2.0,
                                    "MFBOELKCPDP": 6.0
                                }
                            }
                        },
                        {
                            "$type": "TriggerBullet",
                            "NGAAOMEHOGE": 42201005,
                            "NGDMCBABOJA": {
                                "$type": "ConfigBornByGlobalValue",
                                "NHPNHKBMAEO": {
                                    "$type": "ConfigDirectionByWorld",
                                    "GLNBFGDJBAJ": {
                                        "_x": -90.0
                                    }
                                },
                                "GDENJEFPMGC": "Gather_BubblePos",
                                "MICIJLHMIIH": ""
                            }
                        }
                    ]
                }
            }
        }
    },
    {
        "Default": {
            "$type": "ConfigAbility",
            "abilityName": "Abyss_Water_GatherAlert",
            "abilityMixins": [
                {
                    "$type": "AttachToStateIDMixin",
                    "stateIDs": [
                        "GatherSuccess_Alert"
                    ],
                    "modifierName": "GatherAlert"
                }
            ],
            "HNEIEGHMLKH": {
                "GatherAlert": {
                    "modifierName": "",
                    "elementDurability": 100.0,
                    "onAdded": [
                        {
                            "$type": "AttachEffect",
                            "effectPattern": "Eff_Monster_Abyss_Water_Gather_Alert"
                        }
                    ]
                }
            }
        }
    },
    {
        "Default": {
            "$type": "ConfigAbility",
            "abilityName": "Abyss_Water_GatherSuccess",
            "HKBHLMNEMKM": [
                {
                    "$type": "RemoveUniqueModifier",
                    "modifierName": "UNIQUE_Abyss_Water_DizzyTimer"
                },
                {
                    "$type": "FireEffect",
                    "effectPattern": "Eff_Monster_Abyss_Water_Gather_AS_Hor",
                    "NGDMCBABOJA": {
                        "$type": "ConfigBornByTarget",
                        "offset": {
                            "AEAAJCIDPED": 0.0,
                            "KAAPLGBEDPM": 1.0,
                            "PHDCJAHHIOG": 0.0
                        }
                    }
                },
                {
                    "$type": "TriggerAttackEvent",
                    "DMCJDGELKBC": {
                        "attackPattern": {
                            "$type": "ConfigAttackCircle",
                            "lifeTime": "TriggerNoRepeat",
                            "NGDMCBABOJA": {
                                "$type": "ConfigBornBySelf",
                                "offset": {
                                    "AEAAJCIDPED": 0.0,
                                    "KAAPLGBEDPM": 0.75,
                                    "PHDCJAHHIOG": 0.0
                                }
                            },
                            "ICGFCBOFFDI": 5.0
                        },
                        "attackInfo": {
                            "attackTag": "",
                            "attenuationTag": "",
                            "attenuationGroup": "default",
                            "attackProperty": {
                                "bonusCriticalHurt": 2.0,
                                "damagePercentageRatio": 0.0,
                                "elementType": "Water",
                                "elementDurability": 50.0,
                                "strikeType": "Default",
                                "enBreak": 200.0
                            },
                            "hitPattern": {
                                "onHitEffectName": "default",
                                "hitImpulseType": "LV5",
                                "hitHaltTimeScale": 0.05000000074505806
                            }
                        }
                    },
                    "OJIFKEOCJGB": "Enemy"
                },
                {
                    "$type": "FireEffect",
                    "effectPattern": "Eff_Monster_Abyss_Water_Gather_AS_Ver",
                    "NGDMCBABOJA": {
                        "$type": "ConfigBornByTarget",
                        "offset": {
                            "AEAAJCIDPED": 0.0,
                            "KAAPLGBEDPM": 0.0,
                            "PHDCJAHHIOG": 0.0
                        }
                    }
                },
                {
                    "$type": "TriggerAttackEvent",
                    "DMCJDGELKBC": {
                        "attackPattern": {
                            "$type": "ConfigAttackBox",
                            "lifeTime": "TriggerNoRepeat",
                            "NGDMCBABOJA": {
                                "$type": "ConfigBornBySelf",
                                "offset": {
                                    "AEAAJCIDPED": 0.0,
                                    "KAAPLGBEDPM": 5.0,
                                    "PHDCJAHHIOG": -0.5
                                }
                            },
                            "size": {
                                "AEAAJCIDPED": 1.0,
                                "KAAPLGBEDPM": 10.0,
                                "PHDCJAHHIOG": 1.0
                            }
                        },
                        "attackInfo": {
                            "attackTag": "",
                            "attenuationTag": "",
                            "attenuationGroup": "default",
                            "attackProperty": {
                                "bonusCriticalHurt": 2.0,
                                "damagePercentageRatio": 0.0,
                                "elementType": "Water",
                                "elementDurability": 50.0,
                                "strikeType": "Default",
                                "enBreak": 200.0
                            },
                            "hitPattern": {
                                "onHitEffectName": "default",
                                "hitImpulseType": "LV5",
                                "hitHaltTimeScale": 0.05000000074505806
                            }
                        }
                    },
                    "OJIFKEOCJGB": "Enemy"
                },
                {
                    "$type": "ActCameraShake",
                    "cameraShake": {
                        "shakeType": "CustomVector",
                        "shakeRange": 0.1599999964237213,
                        "shakeTime": 0.30000001192092896,
                        "shakeDistance": 25.0,
                        "shakeDir": {
                            "_y": 1.0
                        },
                        "extension": {
                            "rangeAttenuation": 0.8999999761581421
                        }
                    }
                },
                {
                    "$type": "AddGlobalValue",
                    "value": 0.0,
                    "HJJEAOMEOFI": "_GATHERFAILEDSTATE_",
                    "EODOIECEPEF": true,
                    "JDHHMBHOOEC": 0.0,
                    "KHAHOELDONA": 0.0
                }
            ],
            "OGFFGLGEOGF": [
                {
                    "$type": "DoWatcherSystemAction",
                    "predicates": [
                        {
                            "$type": "ByTargetGlobalValue",
                            "NPHOOPNDCAC": "Self",
                            "HJJEAOMEOFI": "_GATHERFAILEDSTATE_",
                            "value": 1.0
                        }
                    ],
                    "GPGMPHIIAMD": 82006,
                    "LNGKALMLMGN": true
                }
            ]
        }
    },
    {
        "Default": {
            "$type": "ConfigAbility",
            "abilityName": "Abyss_Water_BlinkEffect",
            "abilityMixins": [
                {
                    "$type": "AttachToStateIDMixin",
                    "stateIDs": [
                        "Blink"
                    ],
                    "modifierName": "Blink_State"
                }
            ],
            "HNEIEGHMLKH": {
                "Blink_State": {
                    "modifierName": "",
                    "elementDurability": 100.0,
                    "onRemoved": [
                        {
                            "$type": "RemoveUniqueModifier",
                            "modifierName": "UNIQUE_Blink_Shield"
                        },
                        {
                            "$type": "RemoveUniqueModifier",
                            "modifierName": "UNIQUE_Blink_Actions"
                        }
                    ]
                },
                "UNIQUE_Blink_Shield": {
                    "modifierName": "",
                    "IEOFBCGJGEK": true,
                    "elementDurability": 100.0,
                    "onAdded": [
                        {
                            "$type": "RemoveUniqueModifier",
                            "modifierName": "UNIQUE_Abyss_Water_ElementShield_Effect"
                        }
                    ],
                    "onRemoved": [
                        {
                            "$type": "TriggerAbility",
                            "predicates": [
                                {
                                    "$type": "ByTargetGlobalValue",
                                    "HJJEAOMEOFI": "_ABILITY_ABYSS_WATER_ELEMENTSHIELD",
                                    "value": 1.0
                                }
                            ],
                            "abilityName": "Abyss_Water_ElementShield_Effect"
                        }
                    ]
                },
                "UNIQUE_Blink_Actions": {
                    "modifierName": "",
                    "IEOFBCGJGEK": true,
                    "elementDurability": 100.0,
                    "onAdded": [
                        {
                            "$type": "FireEffect",
                            "predicates": [
                                {
                                    "$type": "ByTargetGlobalValue",
                                    "HJJEAOMEOFI": "_ELITEAFFIX_AGILITY_ENHANCE",
                                    "value": 1.0
                                }
                            ],
                            "effectPattern": "Eff_Monster_Abyss_Water_Blink_AS",
                            "NGDMCBABOJA": {
                                "$type": "ConfigBornByTarget",
                                "offset": {
                                    "AEAAJCIDPED": 0.0,
                                    "KAAPLGBEDPM": 0.6499999761581421,
                                    "PHDCJAHHIOG": 0.0
                                }
                            }
                        },
                        {
                            "$type": "TriggerAbility",
                            "predicates": [
                                {
                                    "$type": "ByTargetGlobalValue",
                                    "HJJEAOMEOFI": "_ELITEAFFIX_AGILITY_ENHANCE",
                                    "value": 1.0
                                }
                            ],
                            "abilityName": "Abyss_Water_DoBlink_Damage"
                        },
                        {
                            "$type": "AttachModifier",
                            "modifierName": "Blink_Invincible"
                        },
                        {
                            "$type": "AttachModifier",
                            "modifierName": "Blink_DenyLockOn"
                        },
                        {
                            "$type": "TriggerSetVisible"
                        },
                        {
                            "$type": "TriggerHideWeapon",
                            "FLCNICMDANB": [
                                "equip01"
                            ]
                        },
                        {
                            "$type": "HideUIBillBoard",
                            "COCENMAFJGD": true
                        },
                        {
                            "$type": "EnableHitBoxByName",
                            "EACGOCFODIC": [
                                "HitBox",
                                "HeadBox"
                            ]
                        },
                        {
                            "$type": "EnablePushColliderName",
                            "LEHFIPJFKBC": [
                                "PushCollider"
                            ]
                        }
                    ],
                    "onRemoved": [
                        {
                            "$type": "EnableHitBoxByName",
                            "EACGOCFODIC": [
                                "HitBox",
                                "HeadBox"
                            ],
                            "PAHBCOACBAI": true
                        },
                        {
                            "$type": "EnablePushColliderName",
                            "LEHFIPJFKBC": [
                                "PushCollider"
                            ],
                            "PAHBCOACBAI": true
                        },
                        {
                            "$type": "TriggerSetVisible",
                            "ACDFJMCPFGH": true
                        },
                        {
                            "$type": "TriggerHideWeapon",
                            "ACDFJMCPFGH": true,
                            "FLCNICMDANB": [
                                "equip01"
                            ]
                        },
                        {
                            "$type": "HideUIBillBoard"
                        }
                    ]
                },
                "Blink_Invincible": {
                    "modifierName": "",
                    "elementDurability": 100.0,
                    "state": "Invincible"
                },
                "Blink_DenyLockOn": {
                    "modifierName": "",
                    "elementDurability": 100.0,
                    "state": "DenyLockOn"
                }
            },
            "HKBHLMNEMKM": [
                {
                    "$type": "ApplyModifier",
                    "modifierName": "UNIQUE_Blink_Shield"
                },
                {
                    "$type": "ApplyModifier",
                    "modifierName": "UNIQUE_Blink_Actions"
                },
                {
                    "$type": "FireEffect",
                    "effectPattern": "Eff_Monster_Abyss_Water_Blink_BS"
                },
                {
                    "$type": "ClearLockTarget",
                    "NPHOOPNDCAC": "CurLocalAvatar"
                }
            ]
        }
    },
    {
        "Default": {
            "$type": "ConfigAbility",
            "abilityName": "Abyss_Water_BlinkPoint",
            "HKBHLMNEMKM": [
                {
                    "$type": "TryFindBlinkPoint",
                    "NPHOOPNDCAC": "SelfAttackTarget",
                    "DGICDMAKHOJ": 30.0,
                    "JLCCGHLNHOI": 5.0,
                    "GLALMCMAFJF": 7.0
                },
                {
                    "$type": "FireEffect",
                    "effectPattern": "Eff_Monster_Abyss_Water_Blink",
                    "NGDMCBABOJA": {
                        "$type": "ConfigBornByTeleportToPoint"
                    }
                }
            ]
        }
    },
    {
        "Default": {
            "$type": "ConfigAbility",
            "abilityName": "Abyss_Water_DoBlink",
            "HKBHLMNEMKM": [
                {
                    "$type": "DoBlink"
                }
            ]
        }
    },
    {
        "Default": {
            "$type": "ConfigAbility",
            "abilityName": "Abyss_Water_DoBlink_Visible",
            "HKBHLMNEMKM": [
                {
                    "$type": "FireEffect",
                    "effectPattern": "Eff_Monster_Abyss_Water_Blink_AS",
                    "NGDMCBABOJA": {
                        "$type": "ConfigBornByTarget",
                        "offset": {
                            "AEAAJCIDPED": 0.0,
                            "KAAPLGBEDPM": 0.6499999761581421,
                            "PHDCJAHHIOG": 0.0
                        }
                    }
                },
                {
                    "$type": "RemoveUniqueModifier",
                    "modifierName": "UNIQUE_Blink_Actions"
                }
            ]
        }
    },
    {
        "Default": {
            "$type": "ConfigAbility",
            "abilityName": "Abyss_Water_DoBlink_Damage",
            "HKBHLMNEMKM": [
                {
                    "$type": "TriggerAttackEvent",
                    "DMCJDGELKBC": {
                        "attackPattern": {
                            "$type": "ConfigAttackCircle",
                            "lifeTime": "TriggerNoRepeat",
                            "NGDMCBABOJA": {
                                "$type": "ConfigBornBySelf",
                                "offset": {
                                    "AEAAJCIDPED": 0.0,
                                    "KAAPLGBEDPM": 0.0,
                                    "PHDCJAHHIOG": 0.0
                                }
                            },
                            "secondHeight": 2.0,
                            "ICGFCBOFFDI": 2.5
                        },
                        "attackInfo": {
                            "attackTag": "",
                            "attenuationTag": "",
                            "attenuationGroup": "default",
                            "attackProperty": {
                                "bonusCriticalHurt": 1.0,
                                "damagePercentageRatio": 0.0,
                                "elementType": "Water",
                                "elementDurability": 50.0,
                                "strikeType": "Default",
                                "enBreak": 50.0
                            },
                            "hitPattern": {
                                "onHitEffectName": "default",
                                "hitImpulseType": "LV2",
                                "hitHaltTimeScale": 0.05000000074505806
                            }
                        }
                    },
                    "OJIFKEOCJGB": "Enemy"
                }
            ]
        }
    },
    {
        "Default": {
            "$type": "ConfigAbility",
            "abilityName": "Abyss_Water_Blink_AS",
            "HKBHLMNEMKM": [
                {
                    "$type": "RemoveUniqueModifier",
                    "modifierName": "UNIQUE_Blink_Shield"
                }
            ]
        }
    },
    {
        "Default": {
            "$type": "ConfigAbility",
            "abilityName": "Abyss_Water_ForceDefend",
            "abilityMixins": [
                {
                    "$type": "AttachToPoseIDMixin",
                    "poseIDs": [
                        101
                    ],
                    "modifierName": "ForceDefend"
                }
            ],
            "HNEIEGHMLKH": {
                "ForceDefend": {
                    "modifierName": "",
                    "elementDurability": 100.0,
                    "modifierMixins": [
                        {
                            "$type": "MonsterDefendMixin",
                            "stateIDs": [
                                "BeHit",
                                "BeHitThrow"
                            ],
                            "OKFKMBDCDHO": "DefendTrigger",
                            "OKEAOJGNCNJ": 0.20000000298023224,
                            "CLALNDAGFGJ": 0.0,
                            "LCJAOCJNEJJ": 8.0,
                            "EAEELLPBGHO": false,
                            "HFCIHIJGLMA": 0,
                            "GOLCBAPOOLF": [
                                {
                                    "$type": "TriggerAbility",
                                    "abilityName": "Abyss_Water_ForceBlink"
                                },
                                {
                                    "$type": "ClearLockTarget",
                                    "NPHOOPNDCAC": "CurLocalAvatar"
                                }
                            ]
                        }
                    ]
                }
            }
        }
    },
    {
        "Default": {
            "$type": "ConfigAbility",
            "abilityName": "Abyss_Water_ForceBlink",
            "abilityMixins": [
                {
                    "$type": "AttachToStateIDMixin",
                    "stateIDs": [
                        "ForceBlink"
                    ],
                    "modifierName": "ForceBlink_State"
                }
            ],
            "HNEIEGHMLKH": {
                "ForceBlink_State": {
                    "modifierName": "",
                    "elementDurability": 100.0,
                    "onRemoved": [
                        {
                            "$type": "RemoveUniqueModifier",
                            "modifierName": "UNIQUE_ForceBlink_Actions"
                        }
                    ]
                },
                "UNIQUE_ForceBlink_Actions": {
                    "modifierName": "",
                    "IEOFBCGJGEK": true,
                    "elementDurability": 100.0,
                    "onAdded": [
                        {
                            "$type": "AttachModifier",
                            "modifierName": "ForceBlink_Invincible"
                        },
                        {
                            "$type": "AttachModifier",
                            "modifierName": "ForceBlink_DenyLockOn"
                        },
                        {
                            "$type": "TriggerSetVisible"
                        },
                        {
                            "$type": "TriggerHideWeapon",
                            "FLCNICMDANB": [
                                "equip01"
                            ]
                        },
                        {
                            "$type": "HideUIBillBoard",
                            "COCENMAFJGD": true
                        },
                        {
                            "$type": "EnableHitBoxByName",
                            "EACGOCFODIC": [
                                "HitBox",
                                "HeadBox"
                            ]
                        },
                        {
                            "$type": "EnablePushColliderName",
                            "LEHFIPJFKBC": [
                                "PushCollider"
                            ]
                        }
                    ],
                    "onRemoved": [
                        {
                            "$type": "EnableHitBoxByName",
                            "EACGOCFODIC": [
                                "HitBox",
                                "HeadBox"
                            ],
                            "PAHBCOACBAI": true
                        },
                        {
                            "$type": "EnablePushColliderName",
                            "LEHFIPJFKBC": [
                                "PushCollider"
                            ],
                            "PAHBCOACBAI": true
                        },
                        {
                            "$type": "TriggerSetVisible",
                            "ACDFJMCPFGH": true
                        },
                        {
                            "$type": "TriggerHideWeapon",
                            "ACDFJMCPFGH": true,
                            "FLCNICMDANB": [
                                "equip01"
                            ]
                        },
                        {
                            "$type": "HideUIBillBoard"
                        }
                    ]
                },
                "ForceBlink_Invincible": {
                    "modifierName": "",
                    "elementDurability": 100.0,
                    "state": "Invincible"
                },
                "ForceBlink_DenyLockOn": {
                    "modifierName": "",
                    "elementDurability": 100.0,
                    "state": "DenyLockOn"
                }
            },
            "HKBHLMNEMKM": [
                {
                    "$type": "RemoveUniqueModifier",
                    "modifierName": "UNIQUE_Abyss_Water_DizzyTimer"
                },
                {
                    "$type": "TryFindBlinkPoint",
                    "NPHOOPNDCAC": "SelfAttackTarget",
                    "DGICDMAKHOJ": 30.0,
                    "JLCCGHLNHOI": 9.0,
                    "GLALMCMAFJF": 12.0
                },
                {
                    "$type": "ApplyModifier",
                    "modifierName": "UNIQUE_ForceBlink_Actions"
                },
                {
                    "$type": "FireEffect",
                    "effectPattern": "Eff_Monster_Abyss_Water_Blink_BS"
                }
            ]
        }
    },
    {
        "Default": {
            "$type": "ConfigAbility",
            "abilityName": "Abyss_Water_ForceBlink_DoBlink",
            "HKBHLMNEMKM": [
                {
                    "$type": "DoBlink"
                },
                {
                    "$type": "FireEffect",
                    "effectPattern": "Eff_Monster_Abyss_Water_Blink_AS",
                    "NGDMCBABOJA": {
                        "$type": "ConfigBornByAttachPoint",
                        "KJNJNKLLNCN": "RootNode"
                    }
                }
            ]
        }
    },
    {
        "Default": {
            "$type": "ConfigAbility",
            "abilityName": "Abyss_Water_ForceBlink_Visible",
            "HKBHLMNEMKM": [
                {
                    "$type": "RemoveUniqueModifier",
                    "modifierName": "UNIQUE_ForceBlink_Actions"
                }
            ]
        }
    },
    {
        "Default": {
            "$type": "ConfigAbility",
            "abilityName": "Abyss_Water_ForceBlink_AS",
            "HKBHLMNEMKM": [
                {
                    "$type": "SetPoseInt",
                    "intID": "ElementState",
                    "weight": 1
                }
            ]
        }
    },
    {
        "Default": {
            "$type": "ConfigAbility",
            "abilityName": "Abyss_Water_ReturnToBorn",
            "abilityMixins": [
                {
                    "$type": "AttachToStateIDMixin",
                    "stateIDs": [
                        "ReturnToBorn"
                    ],
                    "modifierName": "ReturnToBorn_Disappear"
                }
            ],
            "HNEIEGHMLKH": {
                "ReturnToBorn_Disappear": {
                    "modifierName": "",
                    "elementDurability": 100.0,
                    "onAdded": [
                        {
                            "$type": "SetGlobalValue",
                            "value": 1.0,
                            "HJJEAOMEOFI": "_RETURNTOBORN_TAG_",
                            "JDHHMBHOOEC": 0.0,
                            "KHAHOELDONA": 0.0
                        },
                        {
                            "$type": "AttachModifier",
                            "modifierName": "UNIQUE_ReturnToBorn_Shield"
                        },
                        {
                            "$type": "AttachModifier",
                            "modifierName": "UNIQUE_ReturnToBorn_Actions"
                        },
                        {
                            "$type": "AttachModifier",
                            "modifierName": "UNIQUE_ReturnToBorn_Dizzy"
                        },
                        {
                            "$type": "FireEffect",
                            "effectPattern": "Eff_Monster_Abyss_Water_Blink_BS"
                        }
                    ],
                    "onRemoved": [
                        {
                            "$type": "SetGlobalValue",
                            "value": 0.0,
                            "HJJEAOMEOFI": "_RETURNTOBORN_TAG_",
                            "JDHHMBHOOEC": 0.0,
                            "KHAHOELDONA": 0.0
                        }
                    ]
                },
                "UNIQUE_ReturnToBorn_Shield": {
                    "modifierName": "",
                    "IEOFBCGJGEK": true,
                    "elementDurability": 100.0,
                    "onAdded": [
                        {
                            "$type": "RemoveUniqueModifier",
                            "modifierName": "UNIQUE_Abyss_Water_ElementShield"
                        },
                        {
                            "$type": "ResetAnimatorTrigger",
                            "triggerID": "ShiledBrokenTrigger"
                        },
                        {
                            "$type": "AttachModifier",
                            "modifierName": "ReturnToBorn_Invincible"
                        },
                        {
                            "$type": "AttachModifier",
                            "modifierName": "ReturnToBorn_DenyLockOn"
                        }
                    ],
                    "onRemoved": [
                        {
                            "$type": "SetPoseInt",
                            "intID": "ElementState",
                            "weight": 2
                        },
                        {
                            "$type": "TriggerAbility",
                            "abilityName": "Abyss_Water_ElementShield_Effect"
                        }
                    ]
                },
                "UNIQUE_ReturnToBorn_Dizzy": {
                    "modifierName": "",
                    "IEOFBCGJGEK": true,
                    "elementDurability": 100.0,
                    "onRemoved": [
                        {
                            "$type": "RemoveUniqueModifier",
                            "modifierName": "UNIQUE_Abyss_Water_DizzyTimer"
                        },
                        {
                            "$type": "SetPoseInt",
                            "intID": "ElementState",
                            "weight": 2
                        },
                        {
                            "$type": "TriggerAbility",
                            "abilityName": "Abyss_Water_ElementShield"
                        },
                        {
                            "$type": "TriggerAbility",
                            "abilityName": "Abyss_Water_ElementShield_Effect"
                        }
                    ]
                },
                "UNIQUE_ReturnToBorn_Actions": {
                    "modifierName": "",
                    "IEOFBCGJGEK": true,
                    "elementDurability": 100.0,
                    "onAdded": [
                        {
                            "$type": "TriggerSetVisible"
                        },
                        {
                            "$type": "TriggerHideWeapon",
                            "FLCNICMDANB": [
                                "equip01"
                            ]
                        },
                        {
                            "$type": "HideUIBillBoard",
                            "COCENMAFJGD": true
                        },
                        {
                            "$type": "EnableHitBoxByName",
                            "EACGOCFODIC": [
                                "HitBox",
                                "HeadBox",
                                "HitBox_ElementShield"
                            ]
                        },
                        {
                            "$type": "EnablePushColliderName",
                            "LEHFIPJFKBC": [
                                "PushCollider",
                                "PushCollider_ElementShield"
                            ]
                        }
                    ],
                    "onRemoved": [
                        {
                            "$type": "TriggerSetVisible",
                            "ACDFJMCPFGH": true
                        },
                        {
                            "$type": "TriggerHideWeapon",
                            "ACDFJMCPFGH": true,
                            "FLCNICMDANB": [
                                "equip01"
                            ]
                        },
                        {
                            "$type": "HideUIBillBoard"
                        },
                        {
                            "$type": "EnableHitBoxByName",
                            "EACGOCFODIC": [
                                "HitBox",
                                "HeadBox"
                            ],
                            "PAHBCOACBAI": true
                        },
                        {
                            "$type": "EnablePushColliderName",
                            "LEHFIPJFKBC": [
                                "PushCollider"
                            ],
                            "PAHBCOACBAI": true
                        }
                    ]
                },
                "ReturnToBorn_Invincible": {
                    "modifierName": "",
                    "elementDurability": 100.0,
                    "state": "Invincible"
                },
                "ReturnToBorn_DenyLockOn": {
                    "modifierName": "",
                    "elementDurability": 100.0,
                    "state": "DenyLockOn"
                }
            },
            "onAdded": [
                {
                    "$type": "SetGlobalValue",
                    "value": 0.0,
                    "HJJEAOMEOFI": "_RETURNTOBORN_TAG_",
                    "JDHHMBHOOEC": 0.0,
                    "KHAHOELDONA": 0.0
                }
            ]
        }
    },
    {
        "Default": {
            "$type": "ConfigAbility",
            "abilityName": "Abyss_Water_ReturnToBorn_AS",
            "HKBHLMNEMKM": [
                {
                    "$type": "FireEffect",
                    "effectPattern": "Eff_Monster_Abyss_Water_Blink_AS",
                    "NGDMCBABOJA": {
                        "$type": "ConfigBornByTarget",
                        "offset": {
                            "AEAAJCIDPED": 0.0,
                            "KAAPLGBEDPM": 0.6499999761581421,
                            "PHDCJAHHIOG": 0.0
                        }
                    }
                },
                {
                    "$type": "RemoveUniqueModifier",
                    "modifierName": "UNIQUE_ReturnToBorn_Dizzy"
                }
            ]
        }
    },
    {
        "Default": {
            "$type": "ConfigAbility",
            "abilityName": "Abyss_Water_ReturnToBorn_Visible",
            "HKBHLMNEMKM": [
                {
                    "$type": "RemoveUniqueModifier",
                    "modifierName": "UNIQUE_ReturnToBorn_Actions"
                }
            ]
        }
    },
    {
        "Default": {
            "$type": "ConfigAbility",
            "abilityName": "Abyss_Water_ReturnToBorn_ElementShield",
            "HKBHLMNEMKM": [
                {
                    "$type": "RemoveUniqueModifier",
                    "modifierName": "UNIQUE_ReturnToBorn_Shield"
                }
            ]
        }
    },
    {
        "Default": {
            "$type": "ConfigAbility",
            "abilityName": "Abyss_Water_WaterBall",
            "abilityMixins": [
                {
                    "$type": "AttachToAnimatorStateIDMixin",
                    "stateIDs": [
                        "NormalAtk"
                    ],
                    "modifierName": "Normal_WeaponEffect"
                }
            ],
            "HNEIEGHMLKH": {
                "Normal_WeaponEffect": {
                    "modifierName": "",
                    "elementDurability": 100.0,
                    "onAdded": [
                        {
                            "$type": "AttachEffect",
                            "effectPattern": "Eff_Monster_Abyss_Water_Normal_WeaponElement"
                        },
                        {
                            "$type": "AttachEffect",
                            "effectPattern": "Eff_Monster_Abyss_Water_WeaponElement"
                        }
                    ]
                }
            },
            "HKBHLMNEMKM": [
                {
                    "$type": "RemoveModifier",
                    "modifierName": "Normal_WeaponEffect"
                },
                {
                    "$type": "SetAnimatorInt",
                    "intID": "RandomFlag",
                    "value": 300.0
                },
                {
                    "$type": "SetAnimatorInt",
                    "predicates": [
                        {
                            "$type": "ByTargetGlobalValue",
                            "HJJEAOMEOFI": "_ELITEAFFIX_AGILITY_ENHANCE",
                            "value": 0.0,
                            "ONPJJFKDCED": "NoneOrEqual"
                        },
                        {
                            "$type": "ByTargetGlobalValue",
                            "HJJEAOMEOFI": "_ELITEAFFIX_ATTACK_ENHANCE",
                            "value": 0.0,
                            "ONPJJFKDCED": "NoneOrEqual"
                        }
                    ],
                    "intID": "RandomFlag",
                    "value": 400.0
                },
                {
                    "$type": "TriggerBullet",
                    "NGAAOMEHOGE": 42201001,
                    "NGDMCBABOJA": {
                        "$type": "ConfigBornByTarget",
                        "offset": {
                            "AEAAJCIDPED": 0.0,
                            "KAAPLGBEDPM": 1.5,
                            "PHDCJAHHIOG": 1.0
                        },
                        "NHPNHKBMAEO": {
                            "$type": "ConfigDirectionByAttackTarget"
                        }
                    }
                }
            ]
        }
    },
    {
        "Default": {
            "$type": "ConfigAbility",
            "abilityName": "Abyss_Water_WaterBall_Loop",
            "HNEIEGHMLKH": {
                "UNIQUE_WaterBall_Loop": {
                    "modifierName": "",
                    "IEOFBCGJGEK": true,
                    "elementType": "Water",
                    "elementDurability": 50.0,
                    "onAdded": [
                        {
                            "$type": "AttachEffect",
                            "effectPattern": "Eff_Monster_Abyss_Water_Bullet"
                        }
                    ],
                    "onRemoved": [
                        {
                            "$type": "KillSelf"
                        }
                    ]
                }
            },
            "onAdded": [
                {
                    "$type": "AttachModifier",
                    "modifierName": "UNIQUE_WaterBall_Loop"
                }
            ]
        }
    },
    {
        "Default": {
            "$type": "ConfigAbility",
            "abilityName": "Abyss_Water_WaterBall_Explode",
            "HKBHLMNEMKM": [
                {
                    "$type": "RemoveUniqueModifier",
                    "modifierName": "UNIQUE_WaterBall_Loop"
                },
                {
                    "$type": "RemoveUniqueModifier",
                    "modifierName": "UNIQUE_Gather_WaterBall_Loop"
                },
                {
                    "$type": "FireEffect",
                    "effectPattern": "Eff_Monster_Abyss_Water_Bullet_AS"
                },
                {
                    "$type": "TriggerAttackEvent",
                    "DMCJDGELKBC": {
                        "attackPattern": {
                            "$type": "ConfigAttackSphere",
                            "lifeTime": "TriggerNoRepeat",
                            "NGDMCBABOJA": {
                                "$type": "ConfigBornBySelf",
                                "offset": {
                                    "AEAAJCIDPED": 0.0,
                                    "KAAPLGBEDPM": 0.25,
                                    "PHDCJAHHIOG": 0.0
                                }
                            },
                            "ICGFCBOFFDI": 1.0
                        },
                        "attackInfo": {
                            "attackTag": "",
                            "attenuationTag": "",
                            "attenuationGroup": "default",
                            "attackProperty": {
                                "bonusCriticalHurt": 1.0,
                                "damagePercentageRatio": 0.0,
                                "elementType": "Water",
                                "elementDurability": 50.0,
                                "strikeType": "Default",
                                "enBreak": 80.0,
                                "attackType": "Range"
                            },
                            "hitPattern": {
                                "onHitEffectName": "default",
                                "hitImpulseType": "LV2",
                                "hitHaltTimeScale": 0.05000000074505806
                            },
                            "canBeModifiedBy": "OriginOwner"
                        }
                    },
                    "OJIFKEOCJGB": "Enemy"
                }
            ]
        }
    },
    {
        "Default": {
            "$type": "ConfigAbility",
            "abilityName": "Abyss_Water_Gather_WaterBall_Loop",
            "HNEIEGHMLKH": {
                "UNIQUE_Gather_WaterBall_Loop": {
                    "modifierName": "",
                    "IEOFBCGJGEK": true,
                    "elementType": "Water",
                    "elementDurability": 50.0,
                    "onAdded": [
                        {
                            "$type": "AttachEffect",
                            "effectPattern": "Eff_Monster_Abyss_Water_BulletFloat"
                        }
                    ],
                    "onRemoved": [
                        {
                            "$type": "KillSelf"
                        }
                    ]
                }
            },
            "onAdded": [
                {
                    "$type": "AttachModifier",
                    "modifierName": "UNIQUE_Gather_WaterBall_Loop"
                }
            ]
        }
    },
    {
        "Default": {
            "$type": "ConfigAbility",
            "abilityName": "Abyss_Water_Gather_Bubble_Loop",
            "HNEIEGHMLKH": {
                "UNIQUE_Gather_Bubble_Loop": {
                    "modifierName": "",
                    "IEOFBCGJGEK": true,
                    "elementType": "Water",
                    "elementDurability": 100.0,
                    "onAdded": [
                        {
                            "$type": "AttachEffect",
                            "effectPattern": "Eff_Monster_Abyss_Water_Bubble_Missle_Float"
                        }
                    ],
                    "onRemoved": [
                        {
                            "$type": "KillSelf"
                        }
                    ],
                    "onBeingHit": [
                        {
                            "$type": "TriggerAbility",
                            "predicates": [
                                {
                                    "$type": "ByHitImpulse",
                                    "DJNJFCLGCMM": 0.0
                                }
                            ],
                            "abilityName": "Abyss_Water_Bubble_Explode"
                        }
                    ]
                }
            },
            "onAdded": [
                {
                    "$type": "AttachModifier",
                    "modifierName": "UNIQUE_Gather_Bubble_Loop"
                }
            ]
        }
    },
    {
        "Default": {
            "$type": "ConfigAbility",
            "abilityName": "Abyss_Water_Bubble_BS",
            "HKBHLMNEMKM": [
                {
                    "$type": "FireEffect",
                    "effectPattern": "Eff_Monster_Abyss_Water_Bubble_Missle_BS"
                },
                {
                    "$type": "SetAnimatorInt",
                    "intID": "RandomFlag",
                    "value": 300.0
                },
                {
                    "$type": "SetAnimatorInt",
                    "predicates": [
                        {
                            "$type": "ByTargetGlobalValue",
                            "HJJEAOMEOFI": "_ELITEAFFIX_AGILITY_ENHANCE",
                            "value": 0.0,
                            "ONPJJFKDCED": "NoneOrEqual"
                        },
                        {
                            "$type": "ByTargetGlobalValue",
                            "HJJEAOMEOFI": "_ELITEAFFIX_ATTACK_ENHANCE",
                            "value": 0.0,
                            "ONPJJFKDCED": "NoneOrEqual"
                        }
                    ],
                    "intID": "RandomFlag",
                    "value": 500.0
                }
            ]
        }
    },
    {
        "Default": {
            "$type": "ConfigAbility",
            "abilityName": "Abyss_Water_Bubble",
            "abilityMixins": [
                {
                    "$type": "AttachToAnimatorStateIDMixin",
                    "stateIDs": [
                        "SpecialAtk"
                    ],
                    "modifierName": "Special_WeaponEffect"
                }
            ],
            "HNEIEGHMLKH": {
                "Special_WeaponEffect": {
                    "modifierName": "",
                    "elementDurability": 100.0,
                    "onAdded": [
                        {
                            "$type": "AttachEffect",
                            "effectPattern": "Eff_Monster_Abyss_Water_Special_WeaponElement"
                        },
                        {
                            "$type": "AttachEffect",
                            "effectPattern": "Eff_Monster_Abyss_Water_WeaponElement"
                        },
                        {
                            "$type": "AddGlobalValue",
                            "value": -1.0,
                            "HJJEAOMEOFI": "_ABILITY_ABYSS_WATER_GATHER",
                            "EODOIECEPEF": true,
                            "JDHHMBHOOEC": 1.0,
                            "KHAHOELDONA": 0.0
                        }
                    ]
                }
            },
            "HKBHLMNEMKM": [
                {
                    "$type": "RemoveModifier",
                    "modifierName": "Special_WeaponEffect"
                },
                {
                    "$type": "TriggerBullet",
                    "NGAAOMEHOGE": 42201002,
                    "NGDMCBABOJA": {
                        "$type": "ConfigBornByTarget",
                        "offset": {
                            "AEAAJCIDPED": 0.0,
                            "KAAPLGBEDPM": 1.5,
                            "PHDCJAHHIOG": 2.0
                        },
                        "NHPNHKBMAEO": {
                            "$type": "ConfigDirectionByAttackTarget"
                        }
                    }
                }
            ]
        }
    },
    {
        "Default": {
            "$type": "ConfigAbility",
            "abilityName": "Abyss_Water_Bubble_Loop",
            "HNEIEGHMLKH": {
                "UNIQUE_Bubble_Loop": {
                    "modifierName": "",
                    "IEOFBCGJGEK": true,
                    "elementType": "Water",
                    "elementDurability": 100.0,
                    "onAdded": [
                        {
                            "$type": "AttachEffect",
                            "effectPattern": "Eff_Monster_Abyss_Water_Bubble_Missle"
                        }
                    ],
                    "onRemoved": [
                        {
                            "$type": "KillSelf"
                        }
                    ],
                    "onBeingHit": [
                        {
                            "$type": "TriggerAbility",
                            "predicates": [
                                {
                                    "$type": "ByHitImpulse",
                                    "DJNJFCLGCMM": 0.0
                                }
                            ],
                            "abilityName": "Abyss_Water_Bubble_Explode"
                        }
                    ]
                }
            },
            "onAdded": [
                {
                    "$type": "AttachModifier",
                    "modifierName": "UNIQUE_Bubble_Loop"
                }
            ]
        }
    },
    {
        "Default": {
            "$type": "ConfigAbility",
            "abilityName": "Abyss_Water_Bubble_Explode",
            "HKBHLMNEMKM": [
                {
                    "$type": "RemoveUniqueModifier",
                    "modifierName": "UNIQUE_Bubble_Loop"
                },
                {
                    "$type": "RemoveUniqueModifier",
                    "modifierName": "UNIQUE_Gather_Bubble_Loop"
                },
                {
                    "$type": "Predicated",
                    "NPHOOPNDCAC": "Owner",
                    "ELDBAFHCOBL": [
                        {
                            "$type": "ByTargetGlobalValue",
                            "HJJEAOMEOFI": "_ABILITY_ABYSS_WATER_GATHER",
                            "value": 1.0
                        }
                    ],
                    "NCNDEAPMKCP": [
                        {
                            "$type": "FireEffect",
                            "effectPattern": "Eff_Monster_Abyss_Water_Bubble_Missle_Float_AS",
                            "NGDMCBABOJA": {
                                "$type": "ConfigBornByAttachPoint",
                                "KJNJNKLLNCN": "RootNode"
                            }
                        }
                    ],
                    "BMIOBLGLPIM": [
                        {
                            "$type": "FireEffect",
                            "effectPattern": "Eff_Monster_Abyss_Water_Bubble_Missle_AS",
                            "NGDMCBABOJA": {
                                "$type": "ConfigBornByAttachPoint",
                                "KJNJNKLLNCN": "RootNode"
                            }
                        }
                    ]
                },
                {
                    "$type": "TriggerBullet",
                    "predicates": [
                        {
                            "$type": "ByTargetGlobalValue",
                            "NPHOOPNDCAC": "OriginOwner",
                            "HJJEAOMEOFI": "_ELITEAFFIX_ATTACK_ENHANCE",
                            "value": 1.0
                        },
                        {
                            "$type": "ByTargetGlobalValue",
                            "HJJEAOMEOFI": "_BUBBLE_TRIGGER_TAG",
                            "value": 0.0,
                            "ONPJJFKDCED": "NoneOrEqual"
                        }
                    ],
                    "NGAAOMEHOGE": 42201016,
                    "NGDMCBABOJA": {
                        "$type": "ConfigBornBySelf"
                    }
                },
                {
                    "$type": "TriggerAttackEvent",
                    "DMCJDGELKBC": {
                        "attackPattern": {
                            "$type": "ConfigAttackSphere",
                            "lifeTime": "TriggerNoRepeat",
                            "NGDMCBABOJA": {
                                "$type": "ConfigBornBySelf",
                                "offset": {
                                    "AEAAJCIDPED": 0.0,
                                    "KAAPLGBEDPM": 0.0,
                                    "PHDCJAHHIOG": 0.0
                                }
                            },
                            "ICGFCBOFFDI": 1.5
                        },
                        "attackInfo": {
                            "attackTag": "",
                            "attenuationTag": "",
                            "attenuationGroup": "default",
                            "attackProperty": {
                                "bonusCriticalHurt": 1.0,
                                "damagePercentageRatio": 0.0,
                                "elementType": "Water",
                                "elementDurability": 100.0,
                                "strikeType": "Default",
                                "enBreak": 100.0,
                                "attackType": "Range"
                            },
                            "hitPattern": {
                                "onHitEffectName": "default",
                                "hitImpulseType": "LV2",
                                "hitHaltTimeScale": 0.05000000074505806
                            },
                            "canBeModifiedBy": "OriginOwner"
                        }
                    },
                    "OJIFKEOCJGB": "Enemy"
                }
            ]
        }
    },
    {
        "Default": {
            "$type": "ConfigAbility",
            "abilityName": "Abyss_Water_Bubble_Surround",
            "HNEIEGHMLKH": {
                "Bubble_Surround_Reject": {
                    "modifierName": "",
                    "GMIMMDOGGIO": 0.10000000149011612,
                    "elementDurability": 100.0,
                    "onAdded": [
                        {
                            "$type": "ApplyModifier",
                            "NPHOOPNDCAC": "Owner",
                            "modifierName": "Bubble_Surround"
                        }
                    ]
                },
                "Bubble_AntiGravity": {
                    "modifierName": "",
                    "GMIMMDOGGIO": 0.30000001192092896,
                    "elementDurability": 100.0,
                    "properties": {
                        "Actor_AddGravityScale": -7.5
                    }
                },
                "Bubble_Surround": {
                    "modifierName": "",
                    "GMIMMDOGGIO": 5.0,
                    "elementType": "Water",
                    "elementDurability": 100.0,
                    "properties": {
                        "Actor_AddGravityScale": -2.0
                    },
                    "state": "Struggle",
                    "onAdded": [
                        {
                            "$type": "AttachModifier",
                            "modifierName": "Bubble_AntiGravity"
                        },
                        {
                            "$type": "AttachEffect",
                            "effectPattern": "Eff_Monster_Abyss_Water_Bubble"
                        }
                    ],
                    "onRemoved": [
                        {
                            "$type": "FireEffect",
                            "effectPattern": "Eff_Monster_Abyss_Water_Bubble_AS",
                            "NGDMCBABOJA": {
                                "$type": "ConfigBornByAttachPoint",
                                "KJNJNKLLNCN": "RootNode"
                            }
                        }
                    ],
                    "onBeingHit": [
                        {
                            "$type": "Predicated",
                            "NPHOOPNDCAC": "Target",
                            "ELDBAFHCOBL": [
                                {
                                    "$type": "ByTargetType",
                                    "GAIGNEFHDBL": false
                                },
                                {
                                    "$type": "ByHitImpulse",
                                    "DJNJFCLGCMM": 0.0
                                }
                            ],
                            "NCNDEAPMKCP": [
                                {
                                    "$type": "RemoveModifier",
                                    "modifierName": "Bubble_Surround"
                                }
                            ]
                        }
                    ],
                    "OGFFGLGEOGF": [
                        {
                            "$type": "RemoveModifier",
                            "modifierName": "Bubble_Surround"
                        }
                    ]
                }
            },
            "HKBHLMNEMKM": [
                {
                    "$type": "Predicated",
                    "NPHOOPNDCAC": "Target",
                    "ELDBAFHCOBL": [
                        {
                            "$type": "ByAny",
                            "predicates": [
                                {
                                    "$type": "ByEntityTypes",
                                    "entityTypes": [
                                        "Gadget"
                                    ]
                                },
                                {
                                    "$type": "ByTargetWeight",
                                    "IHCNHDLDFKC": 100.0
                                }
                            ]
                        }
                    ],
                    "NCNDEAPMKCP": [
                        {
                            "$type": "TriggerAbility",
                            "abilityName": "Abyss_Water_Bubble_Explode"
                        }
                    ],
                    "BMIOBLGLPIM": [
                        {
                            "$type": "TriggerAbility",
                            "abilityName": "Abyss_Water_Bubble_Explode"
                        },
                        {
                            "$type": "ApplyModifier",
                            "NPHOOPNDCAC": "Target",
                            "predicates": [
                                {
                                    "$type": "ByEntityTypes",
                                    "entityTypes": [
                                        "Equip",
                                        "MonsterEquip"
                                    ]
                                }
                            ],
                            "modifierName": "Bubble_Surround_Reject"
                        },
                        {
                            "$type": "ApplyModifier",
                            "NPHOOPNDCAC": "Target",
                            "predicates": [
                                {
                                    "$type": "ByEntityTypes",
                                    "entityTypes": [
                                        "Avatar",
                                        "Monster"
                                    ]
                                }
                            ],
                            "modifierName": "Bubble_Surround"
                        }
                    ]
                }
            ]
        }
    },
    {
        "Default": {
            "$type": "ConfigAbility",
            "abilityName": "Abyss_Water_Bubble_Still",
            "onAdded": [
                {
                    "$type": "AddGlobalValue",
                    "value": 1.0,
                    "HJJEAOMEOFI": "_BUBBLE_TRIGGER_TAG",
                    "EODOIECEPEF": true,
                    "JDHHMBHOOEC": 1.0,
                    "KHAHOELDONA": 0.0
                }
            ]
        }
    },
    {
        "Default": {
            "$type": "ConfigAbility",
            "abilityName": "Abyss_Water_AnimationSteer",
            "abilityMixins": [
                {
                    "$type": "SteerAttackMixin",
                    "EHNAPMMMNFI": [
                        "NormalAtk"
                    ],
                    "HENDIIJFPCI": 360.0,
                    "NCAENFOANAG": "",
                    "BBHBLAIEHAJ": 12.0
                },
                {
                    "$type": "SteerAttackMixin",
                    "EHNAPMMMNFI": [
                        "SpecialAtk"
                    ],
                    "HENDIIJFPCI": 180.0,
                    "NCAENFOANAG": "",
                    "BBHBLAIEHAJ": 12.0
                },
                {
                    "$type": "SteerAttackMixin",
                    "EHNAPMMMNFI": [
                        "RandomAction"
                    ],
                    "HENDIIJFPCI": 180.0,
                    "NCAENFOANAG": "",
                    "BBHBLAIEHAJ": 12.0
                }
            ]
        }
    }
]