[
    {
        "Default": {
            "$type": "ConfigAbility",
            "abilityName": "Monster_Hound_Riftstalker_RunState",
            "modifiers": {
                "Run_RandomValue": {
                    "modifierName": "",
                    "GMIMMDOGGIO": 0.20000000298023224,
                    "elementDurability": 100.0,
                    "onAdded": [
                        {
                            "$type": "Randomed",
                            "PLKDGIELEEF": 0.30000001192092896,
                            "NCNDEAPMKCP": [
                                {
                                    "$type": "SetAnimatorTrigger",
                                    "triggerID": "RunRandom"
                                }
                            ]
                        }
                    ]
                }
            },
            "onAbilityStart": [
                {
                    "$type": "ApplyModifier",
                    "modifierName": "Run_RandomValue"
                }
            ]
        }
    },
    {
        "Default": {
            "$type": "ConfigAbility",
            "abilityName": "Monster_Hound_Corruption_LoseHP",
            "modifiers": {
                "Hound_Corruption_LoseHP_AttackCheck": {
                    "modifierName": "",
                    "elementDurability": 100.0,
                    "AIJPLNMHBEN": [
                        {
                            "$type": "Predicated",
                            "target": "Target",
                            "ELDBAFHCOBL": [
                                {
                                    "$type": "ByEntityTypes",
                                    "entityTypes": [
                                        "Avatar"
                                    ]
                                },
                                {
                                    "$type": "ByAttackTags",
                                    "NMJGDKCDFOJ": [
                                        "Hound_Corruption_Tag"
                                    ]
                                }
                            ],
                            "NCNDEAPMKCP": [
                                {
                                    "$type": "ApplyModifier",
                                    "target": "TargetTeam",
                                    "predicates": [
                                        {
                                            "$type": "ByNot",
                                            "predicates": [
                                                {
                                                    "$type": "ByDungeonSettled"
                                                }
                                            ]
                                        }
                                    ],
                                    "modifierName": "Hound_Corruption_LoseHP_Logic"
                                },
                                {
                                    "$type": "ApplyModifier",
                                    "target": "TargetTeam",
                                    "predicates": [
                                        {
                                            "$type": "ByNot",
                                            "predicates": [
                                                {
                                                    "$type": "ByDungeonSettled"
                                                }
                                            ]
                                        }
                                    ],
                                    "modifierName": "UNIQUE_Hound_Corruption_LoseHP_Effect_LocalHandler"
                                }
                            ]
                        }
                    ]
                },
                "Hound_Corruption_LoseHP_Logic": {
                    "LAFGKJBLBGP": "Level",
                    "FGJPBKGPNJJ": "Multiple",
                    "modifierName": "",
                    "GMIMMDOGGIO": 9.5,
                    "elementDurability": 100.0,
                    "IKKMDDLDLIN": 1.0,
                    "state": "UnlockFrequencyLimit",
                    "onAdded": [
                        {
                            "$type": "LoseHP",
                            "target": "CurTeamAvatars",
                            "doOffStage": true,
                            "predicates": [
                                {
                                    "$type": "ByNot",
                                    "predicates": [
                                        {
                                            "$type": "ByIsLocalAvatar"
                                        }
                                    ]
                                },
                                {
                                    "$type": "ByTargetHPRatio",
                                    "BCJJBMJKHED": 0.15000000596046448
                                },
                                {
                                    "$type": "ByGameTimeIsLocked"
                                }
                            ],
                            "PDLLIFICICJ": 0.0,
                            "AJAHODOGLMH": 0.004999999888241291,
                            "NPCCIJINMGO": false,
                            "IMKEAGOJBPA": true,
                            "LCEHMPAGCPL": true,
                            "GPDAKLCBNFI": true,
                            "BOJIBPNEOHP": true
                        },
                        {
                            "$type": "LoseHP",
                            "target": "CurTeamAvatars",
                            "doOffStage": true,
                            "predicates": [
                                {
                                    "$type": "ByIsLocalAvatar"
                                },
                                {
                                    "$type": "ByGameTimeIsLocked"
                                }
                            ],
                            "PDLLIFICICJ": 0.0,
                            "AJAHODOGLMH": 0.004999999888241291,
                            "IMKEAGOJBPA": true,
                            "LCEHMPAGCPL": true,
                            "GPDAKLCBNFI": true,
                            "BOJIBPNEOHP": true
                        }
                    ],
                    "PBDDACFFPOE": [
                        {
                            "$type": "LoseHP",
                            "target": "CurTeamAvatars",
                            "doOffStage": true,
                            "predicates": [
                                {
                                    "$type": "ByNot",
                                    "predicates": [
                                        {
                                            "$type": "ByIsLocalAvatar"
                                        }
                                    ]
                                },
                                {
                                    "$type": "ByTargetHPRatio",
                                    "BCJJBMJKHED": 0.15000000596046448
                                },
                                {
                                    "$type": "ByGameTimeIsLocked"
                                }
                            ],
                            "PDLLIFICICJ": 0.0,
                            "AJAHODOGLMH": 0.004999999888241291,
                            "NPCCIJINMGO": false,
                            "IMKEAGOJBPA": true,
                            "LCEHMPAGCPL": true,
                            "GPDAKLCBNFI": true,
                            "BOJIBPNEOHP": true
                        },
                        {
                            "$type": "LoseHP",
                            "target": "CurTeamAvatars",
                            "doOffStage": true,
                            "predicates": [
                                {
                                    "$type": "ByIsLocalAvatar"
                                },
                                {
                                    "$type": "ByGameTimeIsLocked"
                                }
                            ],
                            "PDLLIFICICJ": 0.0,
                            "AJAHODOGLMH": 0.004999999888241291,
                            "IMKEAGOJBPA": true,
                            "LCEHMPAGCPL": true,
                            "GPDAKLCBNFI": true,
                            "BOJIBPNEOHP": true
                        }
                    ],
                    "NHFJDDBKNCM": true,
                    "HFBALDBFOOH": [
                        "Corruption"
                    ]
                },
                "UNIQUE_Hound_Corruption_LoseHP_Effect_LocalHandler": {
                    "FGJPBKGPNJJ": "RefreshUniqueDurability",
                    "modifierName": "",
                    "IEOFBCGJGEK": true,
                    "GMIMMDOGGIO": 9.5,
                    "elementDurability": 100.0,
                    "modifierMixins": [
                        {
                            "$type": "CurLocalAvatarMixinV2",
                            "modifierName": "Hound_Corruption_LoseHP_Effect"
                        },
                        {
                            "$type": "LocalAvatarsMixin",
                            "modifierName": "Hound_Corruption_LoseHP_Icon"
                        }
                    ],
                    "HFBALDBFOOH": [
                        "Corruption"
                    ]
                },
                "Hound_Corruption_LoseHP_Effect": {
                    "modifierName": "",
                    "elementDurability": 100.0,
                    "onAdded": [
                        {
                            "$type": "AttachEffect",
                            "effectPattern": "Eff_Monster_Common_Corruption_LoseHP"
                        },
                        {
                            "$type": "SendEffectTrigger",
                            "MOCGJNIDDAI": "Stage",
                            "type": "Int",
                            "weight": 2,
                            "effectPattern": "Eff_Monster_Common_Corruption_LoseHP"
                        }
                    ]
                },
                "Hound_Corruption_LoseHP_Icon": {
                    "modifierName": "",
                    "elementDurability": 100.0,
                    "ONGKIIJLFCG": 90005
                }
            },
            "onAdded": [
                {
                    "$type": "ApplyModifier",
                    "modifierName": "Hound_Corruption_LoseHP_AttackCheck"
                }
            ]
        }
    },
    {
        "Default": {
            "$type": "ConfigAbility",
            "abilityName": "Monster_Hound_Riftstalker_ExitBattle",
            "abilityMixins": [
                {
                    "$type": "AttachToAIAlertnessMixin",
                    "OCFKMHBNKDL": [
                        0
                    ],
                    "modifierName": "ExitBattle"
                }
            ],
            "modifiers": {
                "ExitBattle": {
                    "modifierName": "",
                    "elementDurability": 100.0,
                    "onAdded": [
                        {
                            "$type": "SetGlobalValue",
                            "value": 0.0,
                            "HJJEAOMEOFI": "_Riftstalker_POSE_TAG_",
                            "JDHHMBHOOEC": 0.0,
                            "KHAHOELDONA": 0.0
                        },
                        {
                            "$type": "SetChargeBarValue",
                            "value": 0.0
                        }
                    ]
                }
            }
        }
    }
]