[
    {
        "Default": {
            "$type": "ConfigAbility",
            "abilityName": "SceneObj_Amber_GoldenAmber",
            "abilityMixins": [
                {
                    "$type": "AttachToGadgetStateMixin",
                    "modifierName": "GoldenAmber"
                },
                {
                    "$type": "AttachToGadgetStateMixin",
                    "IJNIFFOPHNJ": 201,
                    "modifierName": "HideMesh"
                }
            ],
            "modifiers": {
                "HideMesh": {
                    "modifierName": "",
                    "elementDurability": 100.0,
                    "onAdded": [
                        {
                            "$type": "EnableSceneTransformByName",
                            "DODBNEDGHLA": [
                                "Collider"
                            ]
                        }
                    ]
                },
                "GoldenAmber": {
                    "modifierName": "",
                    "elementType": "Rock",
                    "elementDurability": 50.0,
                    "modifierMixins": [
                        {
                            "$type": "ShieldBarMixin",
                            "FMAPKFDKKPB": ""
                        }
                    ],
                    "onAdded": [
                        {
                            "$type": "EnableSceneTransformByName",
                            "DODBNEDGHLA": [
                                "Collider"
                            ],
                            "setEnable": true
                        }
                    ],
                    "onRemoved": [
                        {
                            "$type": "FireEffect",
                            "effectPattern": "Eff_Object_Amber_Destory",
                            "born": {
                                "$type": "ConfigBornByTarget",
                                "offset": {
                                    "x": 0.0,
                                    "y": 0.0,
                                    "z": 0.0
                                }
                            }
                        },
                        {
                            "$type": "EnableSceneTransformByName",
                            "DODBNEDGHLA": [
                                "Collider"
                            ]
                        },
                        {
                            "$type": "ExecuteGadgetLua",
                            "JFOEGBAHFAC": 201
                        }
                    ]
                }
            },
            "onAdded": [
                {
                    "$type": "AttachAbilityStateResistance",
                    "KPGAIMMIKDA": 14005
                },
                {
                    "$type": "AttachAbilityStateResistance",
                    "KPGAIMMIKDA": 14002
                }
            ]
        }
    },
    {
        "Default": {
            "$type": "ConfigAbility",
            "abilityName": "SceneObj_Amber_RockAmberBroken",
            "modifiers": {
                "RockAmberBuff": {
                    "modifierName": "",
                    "GMIMMDOGGIO": 60.0,
                    "elementType": "Rock",
                    "elementDurability": 10.0,
                    "properties": {
                        "Entity_WeightRatio": 2.0
                    }
                },
                "Broken": {
                    "modifierName": "",
                    "elementDurability": 100.0,
                    "onRemoved": [
                        {
                            "$type": "ApplyModifier",
                            "otherTargets": {
                                "$type": "SelectTargetsByShape",
                                "JBKKOJLJHDK": "CircleR5",
                                "ONPOPLLHJLE": "All",
                                "CJJABKCAIEB": 1.0
                            },
                            "modifierName": "RockAmberBuff"
                        },
                        {
                            "$type": "FireEffect",
                            "effectPattern": "Eff_Amber_Rock_Hit",
                            "born": {
                                "$type": "ConfigBornByTarget",
                                "offset": {
                                    "x": 0.0,
                                    "y": 0.30000001192092896,
                                    "z": 0.0
                                }
                            }
                        },
                        {
                            "$type": "KillSelf"
                        }
                    ],
                    "onBeingHit": [
                        {
                            "$type": "RemoveModifier",
                            "predicates": [
                                {
                                    "$type": "ByHitDamage",
                                    "GOCKFJJFLHN": 1.0
                                }
                            ],
                            "modifierName": "Broken"
                        }
                    ]
                }
            },
            "onAdded": [
                {
                    "$type": "ApplyModifier",
                    "modifierName": "Broken"
                },
                {
                    "$type": "AttachAbilityStateResistance",
                    "KPGAIMMIKDA": 14005
                },
                {
                    "$type": "AttachAbilityStateResistance",
                    "KPGAIMMIKDA": 14002
                }
            ]
        }
    },
    {
        "Default": {
            "$type": "ConfigAbility",
            "abilityName": "SceneObj_Amber_WaterAmberBroken",
            "modifiers": {
                "Broken": {
                    "modifierName": "",
                    "elementType": "Water",
                    "elementDurability": 50.0,
                    "onRemoved": [
                        {
                            "$type": "CreateGadget",
                            "born": {
                                "$type": "ConfigBornByTarget",
                                "offset": {
                                    "x": 0.0,
                                    "y": 0.0,
                                    "z": 0.0
                                }
                            },
                            "CABLIPAKCGB": 70270002,
                            "DOLAJLACEDF": 5001,
                            "ONPOPLLHJLE": "All"
                        },
                        {
                            "$type": "FireEffect",
                            "effectPattern": "Eff_SceneObj_Amber_Water_Hit",
                            "born": {
                                "$type": "ConfigBornByTarget",
                                "offset": {
                                    "x": 0.0,
                                    "y": 0.30000001192092896,
                                    "z": 0.0
                                }
                            }
                        },
                        {
                            "$type": "KillSelf"
                        }
                    ],
                    "onBeingHit": [
                        {
                            "$type": "RemoveModifier",
                            "predicates": [
                                {
                                    "$type": "ByHitDamage",
                                    "GOCKFJJFLHN": 0.0
                                }
                            ],
                            "modifierName": "Broken"
                        }
                    ]
                }
            },
            "onAdded": [
                {
                    "$type": "ApplyModifier",
                    "modifierName": "Broken"
                },
                {
                    "$type": "AttachAbilityStateResistance",
                    "KPGAIMMIKDA": 14005
                },
                {
                    "$type": "AttachAbilityStateResistance",
                    "KPGAIMMIKDA": 14002
                }
            ]
        }
    },
    {
        "Default": {
            "$type": "ConfigAbility",
            "abilityName": "SceneObj_Amber_WindAmberBroken",
            "modifiers": {
                "Broken": {
                    "modifierName": "",
                    "elementDurability": 100.0,
                    "onRemoved": [
                        {
                            "$type": "CreateGadget",
                            "born": {
                                "$type": "ConfigBornByTarget",
                                "offset": {
                                    "x": 0.0,
                                    "y": 0.0,
                                    "z": 0.0
                                }
                            },
                            "CABLIPAKCGB": 70270003,
                            "DOLAJLACEDF": 1001,
                            "ONPOPLLHJLE": "All"
                        },
                        {
                            "$type": "FireEffect",
                            "effectPattern": "Eff_Amber_Wind_Hit",
                            "born": {
                                "$type": "ConfigBornByTarget",
                                "offset": {
                                    "x": 0.0,
                                    "y": 0.30000001192092896,
                                    "z": 0.0
                                }
                            }
                        },
                        {
                            "$type": "KillSelf"
                        }
                    ],
                    "onBeingHit": [
                        {
                            "$type": "RemoveModifier",
                            "predicates": [
                                {
                                    "$type": "ByHitDamage",
                                    "GOCKFJJFLHN": 1.0
                                }
                            ],
                            "modifierName": "Broken"
                        }
                    ]
                }
            },
            "onAdded": [
                {
                    "$type": "ApplyModifier",
                    "modifierName": "Broken"
                },
                {
                    "$type": "AttachAbilityStateResistance",
                    "KPGAIMMIKDA": 14005
                },
                {
                    "$type": "AttachAbilityStateResistance",
                    "KPGAIMMIKDA": 14002
                }
            ]
        }
    }
]